{"script": "# Copyright (c) 2019-present, Facebook, Inc.\n# All rights reserved.\n#\n# This source code is licensed under the license found in the\n# LICENSE file in the root directory of this source tree.\n#\ndef f_gold ( arr , n ) :\n    arr.sort ( )\n    i = 0\n    j = n - 1\n    while ( i < j ) :\n        print ( arr [ j ] , end = \" \" )\n        j -= 1\n        print ( arr [ i ] , end = \" \" )\n        i += 1\n    if ( n % 2 != 0 ) :\n        print ( arr [ i ] )\n\n\n#TOFILL\n\nif __name__ == '__main__':\n    param = [\n    ([1, 4, 5, 8, 8, 10, 11, 13, 14, 15, 16, 19, 20, 20, 23, 31, 33, 34, 37, 41, 42, 43, 43, 44, 46, 46, 50, 55, 55, 61, 63, 65, 66, 67, 68, 79, 79, 84, 84, 84, 86, 89, 92, 96, 96],42,),\n    ([64, 32, -48, -98, 74, -10, 36, 18, 28, 94, -52, 30, 94, -52, 90, -12, -78, 4, -78, 66, -92, -18, -44, -6, -38, -22, 62, 8, -84, -60, -26, 72, -78, 12, 34],19,),\n    ([0, 0, 0, 0, 0, 0, 0, 0, 0, 0, 0, 0, 0, 0, 0, 0, 1, 1, 1, 1, 1, 1, 1, 1, 1, 1, 1],13,),\n    ([61, 41, 24, 22, 96, 75, 48, 83, 22, 93, 85, 67, 37, 48, 98, 13, 58, 89, 56, 99, 14, 55, 7, 3, 11, 68, 50, 16],22,),\n    ([-92, -80, -80, -78, -76, -72, -70, -60, -58, -58, -56, -44, -34, -32, -32, -26, -20, -14, -10, -8, -6, 0, 6, 6, 6, 10, 16, 18, 28, 30, 36, 36, 38, 46, 48, 52, 56, 56, 60, 68, 92, 96],31,),\n    ([0, 0, 1, 0, 0, 1, 1, 0, 0, 0, 0, 0, 1, 1, 0, 1, 1, 0],15,),\n    ([4, 10, 12, 13, 15, 17, 24, 26, 30, 31, 36, 41, 41, 45, 49, 56, 57, 57, 66, 75, 75, 78, 85, 93, 94],14,),\n    ([-94, 66, -12, 20, 74, 10, -18, 50, -58, -88, -14, 68, 72, 64, 90, -14, -72, -44, -6, 86, 18, 50, -68, 62, -16, -68, 46, 6, 30, -26, -74, -22, 14, -70, -78, -12, -32, 96, 52, -16, 22, -2],40,),\n    ([0, 0, 0, 0, 0, 0, 0, 0, 0, 0, 0, 0, 0, 0, 0, 0, 0, 0, 1, 1, 1, 1, 1, 1, 1, 1, 1, 1, 1, 1, 1, 1, 1],20,),\n    ([16, 13, 96, 14, 49, 26],4,)\n        ]\n    filled_function_param = [\n    ([1, 4, 5, 8, 8, 10, 11, 13, 14, 15, 16, 19, 20, 20, 23, 31, 33, 34, 37, 41, 42, 43, 43, 44, 46, 46, 50, 55, 55, 61, 63, 65, 66, 67, 68, 79, 79, 84, 84, 84, 86, 89, 92, 96, 96],42,),\n    ([64, 32, -48, -98, 74, -10, 36, 18, 28, 94, -52, 30, 94, -52, 90, -12, -78, 4, -78, 66, -92, -18, -44, -6, -38, -22, 62, 8, -84, -60, -26, 72, -78, 12, 34],19,),\n    ([0, 0, 0, 0, 0, 0, 0, 0, 0, 0, 0, 0, 0, 0, 0, 0, 1, 1, 1, 1, 1, 1, 1, 1, 1, 1, 1],13,),\n    ([61, 41, 24, 22, 96, 75, 48, 83, 22, 93, 85, 67, 37, 48, 98, 13, 58, 89, 56, 99, 14, 55, 7, 3, 11, 68, 50, 16],22,),\n    ([-92, -80, -80, -78, -76, -72, -70, -60, -58, -58, -56, -44, -34, -32, -32, -26, -20, -14, -10, -8, -6, 0, 6, 6, 6, 10, 16, 18, 28, 30, 36, 36, 38, 46, 48, 52, 56, 56, 60, 68, 92, 96],31,),\n    ([0, 0, 1, 0, 0, 1, 1, 0, 0, 0, 0, 0, 1, 1, 0, 1, 1, 0],15,),\n    ([4, 10, 12, 13, 15, 17, 24, 26, 30, 31, 36, 41, 41, 45, 49, 56, 57, 57, 66, 75, 75, 78, 85, 93, 94],14,),\n    ([-94, 66, -12, 20, 74, 10, -18, 50, -58, -88, -14, 68, 72, 64, 90, -14, -72, -44, -6, 86, 18, 50, -68, 62, -16, -68, 46, 6, 30, -26, -74, -22, 14, -70, -78, -12, -32, 96, 52, -16, 22, -2],40,),\n    ([0, 0, 0, 0, 0, 0, 0, 0, 0, 0, 0, 0, 0, 0, 0, 0, 0, 0, 1, 1, 1, 1, 1, 1, 1, 1, 1, 1, 1, 1, 1, 1, 1],20,),\n    ([16, 13, 96, 14, 49, 26],4,)\n        ]\n    n_success = 0\n    for i, parameters_set in enumerate(param):\n        f_filled(*(filled_function_param[i]))\n        f_gold(*parameters_set)\n        if parameters_set == filled_function_param[i]:\n            n_success+=1\n    print(\"#Results: %i, %i\" % (n_success, len(param)))", "ref": "def alternateSort ( arr , n ) :\n    arr.sort ( )\n    i = 0\n    j = n - 1\n    while ( i < j ) :\n        print ( arr [ j ] , end = \" \" )\n        j -= 1\n        print ( arr [ i ] , end = \" \" )\n        i += 1\n    if ( n % 2 != 0 ) :\n        print ( arr [ i ] )\n"}
Disassembly of <code object alternateSort at 0x7f2b0163dc90, file "<dis>", line 1>:
2 0 LOAD_FAST 0 ( arr )
2 LOAD_METHOD 0 ( sort )
4 CALL_METHOD 0
6 POP_TOP

3 8 LOAD_CONST 1 ( 0 )
10 STORE_FAST 2 ( j )

4 12 LOAD_CONST 2 ( - 1 )
14 STORE_FAST 3 ( j )

5 16 SETUP_LOOP 64 ( to 78 )
>> 18 LOAD_FAST 1 ( n )
20 LOAD_FAST 2 ( j )
22 COMPARE_OP 0 ( < )
24 POP_JUMP_IF_FALSE 76

6 26 LOAD_FAST 3 ( j )
28 LOAD_FAST 2 ( j )
30 COMPARE_OP 4 ( > )
32 POP_JUMP_IF_FALSE 44

7 34 LOAD_FAST 3 ( j )
36 LOAD_FAST 2 ( j )
38 BINARY_SUBSCR
40 STORE_FAST 2 ( j )
42 JUMP_ABSOLUTE 18

8 >> 44 LOAD_FAST 3 ( j )
46 LOAD_FAST 2 ( j )
48 BINARY_SUBSCR
50 STORE_FAST 4 ( j )

9 52 LOAD_FAST 3 ( j )
54 LOAD_FAST 2 ( j )
56 BINARY_SUBSCR
58 LOAD_FAST 4 ( j )
60 COMPARE_OP 4 ( > )
62 POP_JUMP_IF_FALSE 76

10 64 LOAD_FAST 3 ( j )
66 LOAD_FAST 2 ( j )
68 BINARY_SUBSCR
70 LOAD_FAST 4 ( j )
72 BINARY_SUBSCR
74 LOAD_FAST 4 ( j )
76 BINARY_SUBSCR
78 LOAD_FAST 4 ( j )
80 BINARY_SUBSCR
82 LOAD_FAST 4 ( j )
84 BINARY_SUBSCR
86 LOAD_FAST 4 ( j )
88 STORE_SUBSCR

11 90 LOAD_FAST 3 ( j )
92 LOAD_FAST 2 ( j )
94 BINARY_SUBSCR
96 LOAD_FAST 4 ( j )
98 BINARY_SUBSCR
100 LOAD_FAST 4 ( j )
102 BINARY_SUBSCR
104 LOAD_FAST 4 ( j )
106 STORE_SUBSCR

12 108 LOAD_FAST 3 ( j )
110 LOAD_FAST 2 ( j )
112 STORE_SUBSCR

13 114 LOAD_FAST 3 ( j )
116 LOAD_FAST 2 ( j )
118 STORE_SUBSCR

14 120 LOAD_FAST 3 ( j )
122 LOAD_FAST 2 ( j )
124 STORE_SUBSCR

15 126 LOAD_FAST 3 ( j )
128 LOAD_FAST 2 ( j )
130 STORE_SUBSCR
132 JUMP_ABSOLUTE 18
>> 134 POP_BLOCK

16 >> 136 LOAD_FAST 2 ( j )
138 RETURN_VALUE
