{"script": "# Copyright (c) 2019-present, Facebook, Inc.\n# All rights reserved.\n#\n# This source code is licensed under the license found in the\n# LICENSE file in the root directory of this source tree.\n#\nimport sys\n\ndef f_gold ( str , l , h ) :\n    if ( l > h ) :\n        return sys.maxsize\n    if ( l == h ) :\n        return 0\n    if ( l == h - 1 ) :\n        return 0 if ( str [ l ] == str [ h ] ) else 1\n    if ( str [ l ] == str [ h ] ) :\n        return f_gold ( str , l + 1 , h - 1 )\n    else :\n        return ( min ( f_gold ( str , l , h - 1 ) , f_gold ( str , l + 1 , h ) ) + 1 )\n\n\n#TOFILL\n\nif __name__ == '__main__':\n    param = [\n    (['F', 'F', 'J', 'K', 'K', 'L', 'P', 'S', 'T', 'V', 'W', 'Y', 'b', 'd', 'j', 'l', 't', 'u', 'x', 'y'],11,11,),\n    (['0', '1', '8', '8', '8', '4', '4', '3', '9', '6', '5', '2', '8', '2', '0', '2', '6', '0', '7', '7', '3', '2', '4', '5', '9', '7', '2', '4', '1', '8', '7', '9', '8', '0', '8', '5', '4', '2', '3'],19,22,),\n    (['1'],0,0,),\n    (['g', 'y', 'r', 'M', 'v', 'z', ' ', 'k', 'S', 'P', 'x', 'p', 'E', 'z', 'T', 'K', 'k', 'B', 's', 'P', 'p', 'e', 'G', 't', 'r', 'M', 'p', ' ', 'H', 'a'],24,27,),\n    (['0', '1', '1', '1', '1', '1', '1', '2', '2', '2', '2', '3', '3', '3', '3', '3', '4', '4', '4', '5', '5', '5', '5', '5', '6', '6', '6', '6', '6', '6', '6', '7', '8', '8', '8', '9', '9'],33,34,),\n    (['1', '1', '0', '1', '0', '1', '0', '1', '0', '1', '1', '1', '1', '1', '1', '0'],13,8,),\n    ([' ', ' ', ' ', 'B', 'C', 'C', 'D', 'I', 'K', 'O', 'P', 'R', 'T', 'V', 'W', 'a', 'b', 'd', 'j', 'y'],16,14,),\n    (['5', '0', '8', '6', '9', '3', '0', '3', '2', '0', '6', '2', '3', '7', '8', '9', '2', '0', '1', '9', '4', '1', '3', '1', '9', '2', '3', '4', '1', '2', '3', '8', '1'],31,25,),\n    (['0', '0', '0', '0', '0', '0', '0', '0', '0', '0', '0', '0', '0', '0', '0', '0', '0', '0', '0', '0', '1', '1', '1', '1', '1', '1', '1', '1', '1', '1', '1', '1', '1', '1', '1', '1', '1', '1', '1', '1', '1', '1', '1', '1', '1', '1'],37,35,),\n    (['X', 'B', 'E', 'v', 'K', 't', 'k', 'K', 'Q', 's', 'V', 'N', 'l', 'k', 'T', 'N', 'J', 'z', 'f', 'p', 'J', 'g', 'S', 'P', 'M', 'b', 'H', 'L', 'v', 'E', 'A', 'n', 'D', 'U', 'c', 's', 'M', 'Q', 'P', 'g', 'g', ' '],26,27,)\n        ]\n    n_success = 0\n    for i, parameters_set in enumerate(param):\n        if f_filled(*parameters_set) == f_gold(*parameters_set):\n            n_success+=1\n    print(\"#Results: %i, %i\" % (n_success, len(param)))", "ref": "def findMinInsertions ( str , l , h ) :\n    if ( l > h ) :\n        return sys.maxsize\n    if ( l == h ) :\n        return 0\n    if ( l == h - 1 ) :\n        return 0 if ( str [ l ] == str [ h ] ) else 1\n    if ( str [ l ] == str [ h ] ) :\n        return findMinInsertions ( str , l + 1 , h - 1 )\n    else :\n        return ( min ( findMinInsertions ( str , l , h - 1 ) , findMinInsertions ( str , l + 1 , h ) ) + 1 )\n"}
Disassembly of <code object findMinInsertions at 0x7f2b0163dc90, file "<dis>", line 1>:
2 0 LOAD_FAST 1 ( l )
2 LOAD_FAST 2 ( l )
4 COMPARE_OP 4 ( > )
6 POP_JUMP_IF_FALSE 20

3 8 LOAD_GLOBAL 0 ( sys )
10 LOAD_ATTR 1 ( maxsize )
12 LOAD_FAST 2 ( l )
14 COMPARE_OP 4 ( > )
16 POP_JUMP_IF_FALSE 20

4 18 LOAD_GLOBAL 0 ( sys )
20 LOAD_ATTR 1 ( maxsize )
22 LOAD_FAST 2 ( l )
24 LOAD_CONST 1 ( 1 )
26 BINARY_SUBTRACT
28 BINARY_SUBSCR
30 LOAD_FAST 2 ( l )
32 LOAD_CONST 1 ( 1 )
34 BINARY_SUBTRACT
36 BINARY_SUBSCR
38 LOAD_FAST 2 ( l )
40 LOAD_CONST 1 ( 1 )
42 BINARY_SUBTRACT
44 BINARY_SUBSCR
46 LOAD_FAST 2 ( l )
48 LOAD_CONST 1 ( 1 )
50 BINARY_SUBTRACT
52 BINARY_SUBSCR
54 LOAD_FAST 2 ( l )
56 LOAD_CONST 1 ( 1 )
58 BINARY_SUBTRACT
60 BINARY_SUBSCR
62 BINARY_SUBTRACT
64 LOAD_FAST 2 ( l )
66 LOAD_CONST 1 ( 1 )
68 BINARY_SUBTRACT
70 BINARY_SUBSCR
72 LOAD_FAST 2 ( l )
74 LOAD_CONST 1 ( 1 )
76 BINARY_SUBTRACT
78 BINARY_SUBSCR
80 BINARY_SUBTRACT
82 LOAD_FAST 2 ( l )
84 LOAD_CONST 1 ( 1 )
86 BINARY_SUBTRACT
88 BINARY_SUBSCR
90 BINARY_SUBTRACT
92 LOAD_FAST 2 ( l )
94 LOAD_CONST 1 ( 1 )
96 BINARY_SUBTRACT
98 BINARY_SUBSCR
100 BINARY_SUBTRACT
102 STORE_FAST 2 ( l )

5 104 LOAD_FAST 2 ( l )
106 LOAD_CONST 1 ( 1 )
108 BINARY_SUBTRACT
110 BINARY_SUBSCR
112 LOAD_FAST 2 ( l )
114 LOAD_CONST 1 ( 1 )
116 BINARY_SUBTRACT
118 BINARY_SUBSCR
120 LOAD_FAST 2 ( l )
122 LOAD_CONST 1 ( 1 )
124 BINARY_SUBTRACT
126 BINARY_SUBSCR
128 BINARY_SUBTRACT
130 STORE_FAST 2 ( l )

6 132 LOAD_FAST 2 ( l )
134 LOAD_CONST 1 ( 1 )
136 BINARY_SUBTRACT
138 LOAD_FAST 2 ( l )
140 LOAD_CONST 1 ( 1 )
142 BINARY_SUBTRACT
144 BINARY_SUBSCR
146 LOAD_FAST 2 ( l )
148 LOAD_CONST 1 ( 1 )
150 BINARY_SUBTRACT
152 BINARY_SUBSCR
154 BINARY_SUBTRACT
156 LOAD_FAST 2 ( l )
158 LOAD_CONST 1 ( 1 )
160 BINARY_SUBTRACT
162 BINARY_SUBSCR
164 BINARY_SUBTRACT
166 STORE_FAST 2 ( l )

7 168 LOAD_FAST 2 ( l )
170 LOAD_CONST 1 ( 1 )
172 BINARY_SUBTRACT
174 LOAD_FAST 2 ( l )
176 LOAD_CONST 1 ( 1 )
178 BINARY_SUBTRACT
180 BINARY_SUBTRACT
182 BINARY_SUBTRACT
184 RETURN_VALUE
