{"script": "# Copyright (c) 2019-present, Facebook, Inc.\n# All rights reserved.\n#\n# This source code is licensed under the license found in the\n# LICENSE file in the root directory of this source tree.\n#\ndef f_gold ( arr , n , X ) :\n    if ( X < arr [ 0 ] ) :\n        return 0 ;\n    elif ( X > arr [ n - 1 ] ) :\n        return n\n    lowerPnt = 0\n    i = 1\n    while ( i < n and arr [ i ] < X ) :\n        lowerPnt = i\n        i = i * 2\n    while ( lowerPnt < n and arr [ lowerPnt ] < X ) :\n        lowerPnt += 1\n    return lowerPnt\n\n\n#TOFILL\n\nif __name__ == '__main__':\n    param = [\n    ([1, 2, 5, 5, 16, 16, 20, 26, 32, 35, 39, 39, 41, 44, 48, 48, 51, 59, 59, 62, 66, 66, 70, 74, 75, 78, 80, 86, 86, 96],17,29,),\n    ([-76, 80, -6, -2, 50, 72, 84, -56, 70, 8, 48, 6, -24, -50, -72],14,9,),\n    ([0, 0, 0, 0, 0, 1, 1, 1, 1],8,4,),\n    ([74, 65, 84, 71],2,3,),\n    ([-96, -92, -90, -86, -84, -76, -76, -62, -58, -54, -50, -50, -44, -42, -38, -34, -14, -8, 6, 12, 24, 38, 40, 50, 62, 84, 86, 92],19,19,),\n    ([1, 1, 0, 0, 0, 1, 1, 1, 0, 0, 1, 1, 0, 1, 0, 1, 0, 0, 0, 1, 1, 1, 1],12,17,),\n    ([6, 10, 14, 14, 16, 19, 23, 23, 25, 26, 29, 34, 42, 42, 43, 45, 47, 49, 50, 51, 51, 56, 59, 65, 69, 72, 75, 78, 79, 80, 82, 82, 82, 84, 85, 91, 98],31,24,),\n    ([-90, -2, 22, -2, 58, -2, 96, 38, 36, -66, -98, 22, -80, -32, 22, 0, -34, -16, 82, 76, 12, 84, 66, 8, 32, 18, -98, -10],22,16,),\n    ([0, 0, 0, 1, 1, 1, 1],3,5,),\n    ([85, 59, 22, 52, 93, 14, 42, 71, 69, 15, 52, 78, 35, 61, 92, 90, 70, 48, 47, 72, 74, 46, 22, 74, 83, 32, 14, 24, 18, 27, 18, 68, 29, 31],19,33,)\n        ]\n    n_success = 0\n    for i, parameters_set in enumerate(param):\n        if f_filled(*parameters_set) == f_gold(*parameters_set):\n            n_success+=1\n    print(\"#Results: %i, %i\" % (n_success, len(param)))", "ref": "def LowerInsertionPoint ( arr , n , X ) :\n    if ( X < arr [ 0 ] ) :\n        return 0 ;\n    elif ( X > arr [ n - 1 ] ) :\n        return n\n    lowerPnt = 0\n    i = 1\n    while ( i < n and arr [ i ] < X ) :\n        lowerPnt = i\n        i = i * 2\n    while ( lowerPnt < n and arr [ lowerPnt ] < X ) :\n        lowerPnt += 1\n    return lowerPnt\n"}
Disassembly of <code object LowerInsertionPoint at 0x7f2b0163dc90, file "<dis>", line 1>:
2 0 LOAD_FAST 0 ( arr )
2 LOAD_FAST 1 ( n )
4 LOAD_CONST 1 ( 0 )
6 BINARY_SUBSCR
8 COMPARE_OP 0 ( < )
10 POP_JUMP_IF_FALSE 20
12 LOAD_FAST 1 ( n )
14 LOAD_CONST 1 ( 0 )
16 BINARY_SUBSCR
18 LOAD_CONST 2 ( 1 )
20 COMPARE_OP 4 ( > )
22 POP_JUMP_IF_FALSE 28

3 >> 24 LOAD_CONST 3 ( 0 )
26 RETURN_VALUE

4 >> 28 SETUP_LOOP 64 ( to 92 )
30 LOAD_GLOBAL 0 ( range )
32 LOAD_FAST 1 ( n )
34 LOAD_CONST 1 ( 0 )
36 BINARY_SUBSCR
38 CALL_FUNCTION 1
40 GET_ITER
>> 42 FOR_ITER 48 ( to 90 )
44 STORE_FAST 2 ( i )

5 46 LOAD_FAST 2 ( i )
48 LOAD_CONST 1 ( 0 )
50 BINARY_SUBSCR
52 LOAD_CONST 2 ( 1 )
54 COMPARE_OP 4 ( > )
56 POP_JUMP_IF_FALSE 42

6 58 LOAD_CONST 4 ( 0 )
60 RETURN_VALUE

7 >> 62 LOAD_FAST 0 ( arr )
64 LOAD_FAST 1 ( n )
66 BINARY_SUBSCR
68 LOAD_CONST 2 ( 1 )
70 COMPARE_OP 4 ( > )
72 POP_JUMP_IF_FALSE 42

8 74 LOAD_CONST 5 ( 1 )
76 RETURN_VALUE

9 >> 78 LOAD_FAST 0 ( arr )
80 LOAD_FAST 1 ( n )
82 BINARY_SUBSCR
84 LOAD_CONST 6 ( 's' )
86 COMPARE_OP 2 ( == )
88 POP_JUMP_IF_FALSE 42

10 90 LOAD_CONST 5 ( 1 )
92 RETURN_VALUE

11 >> 94 LOAD_FAST 0 ( arr )
96 LOAD_FAST 1 ( n )
98 BINARY_SUBSCR
100 LOAD_CONST 7 ( 's' )
102 COMPARE_OP 2 ( == )
104 POP_JUMP_IF_FALSE 42

12 106 LOAD_CONST 5 ( 1 )
108 RETURN_VALUE

13 >> 110 LOAD_FAST 0 ( arr )
112 LOAD_FAST 1 ( n )
114 BINARY_SUBSCR
116 LOAD_CONST 8 ( 's' )
118 COMPARE_OP 2 ( == )
120 POP_JUMP_IF_FALSE 42

14 122 LOAD_CONST 5 ( 1 )
124 RETURN_VALUE

15 >> 126 LOAD_FAST 0 ( arr )
128 LOAD_FAST 1 ( n )
130 BINARY_SUBSCR
132 LOAD_CONST 9 ( 's' )
134 COMPARE_OP 2 ( == )
136 POP_JUMP_IF_FALSE 42

16 138 LOAD_CONST 5 ( 1 )
140 RETURN_VALUE

17 >> 142 LOAD_FAST 0 ( arr )
144 LOAD_FAST 1 ( n )
146 BINARY_SUBSCR
148 RETURN_VALUE
