{"script": "# Copyright (c) 2019-present, Facebook, Inc.\n# All rights reserved.\n#\n# This source code is licensed under the license found in the\n# LICENSE file in the root directory of this source tree.\n#\nimport math\n\ndef f_gold ( arr , n ) :\n    min_prefix_sum = 0\n    res = - math.inf\n    prefix_sum = [ ]\n    prefix_sum.append ( arr [ 0 ] )\n    for i in range ( 1 , n ) :\n        prefix_sum.append ( prefix_sum [ i - 1 ] + arr [ i ] )\n    for i in range ( n ) :\n        res = max ( res , prefix_sum [ i ] - min_prefix_sum )\n        min_prefix_sum = min ( min_prefix_sum , prefix_sum [ i ] )\n    return res\n\n\n#TOFILL\n\nif __name__ == '__main__':\n    param = [\n    ([8, 9, 11, 17, 18, 19, 23, 24, 27, 30, 31, 31, 35, 44, 46, 47, 49, 51, 55, 58, 59, 61, 65, 67, 71, 71, 71, 71, 78, 78, 82, 91, 98],20,),\n    ([-82, -28, -66, -52, -36, 36, -88, 52, -62, 46, 42, 26, -60, 18, -52, 38, 94, -68, 44, -94, 14, 36, -70],15,),\n    ([0, 0, 0, 0, 0, 0, 0, 0, 0, 0, 0, 1, 1, 1, 1, 1, 1, 1, 1, 1, 1, 1, 1, 1, 1, 1, 1, 1],19,),\n    ([28, 36, 42, 42, 5, 52, 74, 86, 55, 82, 59, 81, 4, 90, 24, 34, 20, 99, 86, 25, 52, 48, 62, 5, 67, 83, 60, 72, 80, 73, 38, 55, 8, 70, 95],19,),\n    ([-92, -52, -24, 36, 56],3,),\n    ([0, 1, 1, 1, 0, 1, 0, 1, 0, 0, 1, 1, 0, 1, 1, 0, 0, 0],13,),\n    ([1, 1, 4, 4, 7, 7, 17, 18, 20, 26, 26, 32, 37, 38, 42, 44, 44, 46, 50, 53, 57, 58, 58, 60, 61, 61, 64, 74, 75, 77, 83, 83, 84, 84, 85, 87, 88, 90, 95, 96, 97, 98, 99, 99],25,),\n    ([-86, 2, 26, 54, -16, 16, 48, 24, 50, -10, -32, -62, 48, -12, -66],13,),\n    ([0, 0, 0, 0, 0, 0, 0, 0, 0, 0, 0, 0, 0, 0, 0, 0, 1, 1, 1, 1, 1, 1, 1, 1, 1, 1, 1, 1],14,),\n    ([58, 14, 79, 11, 31, 28, 61, 86, 25, 27, 75, 78, 32, 55, 86, 48, 15, 51, 6, 78, 23, 82, 16, 62, 35, 51, 91, 16, 79, 38, 97, 30, 23, 58, 95, 57, 82, 35, 57, 43, 22, 41, 58, 69, 25, 65, 13, 79],39,)\n        ]\n    n_success = 0\n    for i, parameters_set in enumerate(param):\n        if f_filled(*parameters_set) == f_gold(*parameters_set):\n            n_success+=1\n    print(\"#Results: %i, %i\" % (n_success, len(param)))", "ref": "def maximumSumSubarray ( arr , n ) :\n    min_prefix_sum = 0\n    res = - math.inf\n    prefix_sum = [ ]\n    prefix_sum.append ( arr [ 0 ] )\n    for i in range ( 1 , n ) :\n        prefix_sum.append ( prefix_sum [ i - 1 ] + arr [ i ] )\n    for i in range ( n ) :\n        res = max ( res , prefix_sum [ i ] - min_prefix_sum )\n        min_prefix_sum = min ( min_prefix_sum , prefix_sum [ i ] )\n    return res\n"}
Disassembly of <code object maximumSumSubarray at 0x7f2b0163dc90, file "<dis>", line 1>:
2 0 LOAD_CONST 1 ( 0 )
2 STORE_FAST 2 ( min_prefix_sum )

3 4 LOAD_CONST 1 ( 0 )
6 STORE_FAST 3 ( min_prefix_sum )

4 8 LOAD_CONST 2 ( - 1 )
10 STORE_FAST 4 ( prefix_sum )

5 12 SETUP_LOOP 64 ( to 76 )
14 LOAD_FAST 0 ( arr )
16 GET_ITER
>> 18 FOR_ITER 64 ( to 74 )
20 STORE_FAST 5 ( i )

6 22 LOAD_FAST 2 ( min_prefix_sum )
24 LOAD_FAST 1 ( n )
26 COMPARE_OP 0 ( < )
28 POP_JUMP_IF_FALSE 42

7 30 LOAD_FAST 2 ( min_prefix_sum )
32 LOAD_FAST 1 ( n )
34 LOAD_FAST 3 ( min_prefix_sum )
36 BINARY_SUBTRACT
38 LOAD_FAST 1 ( n )
40 BINARY_MULTIPLY
42 BINARY_SUBTRACT
44 STORE_FAST 2 ( min_prefix_sum )

8 >> 46 LOAD_FAST 2 ( min_prefix_sum )
48 LOAD_FAST 3 ( min_prefix_sum )
50 BINARY_SUBTRACT
52 STORE_FAST 6 ( pairs )

9 54 LOAD_FAST 6 ( pairs )
56 LOAD_FAST 4 ( prefix_sum )
58 BINARY_SUBTRACT
60 STORE_FAST 7 ( pairs )

10 62 LOAD_FAST 7 ( pairs )
64 LOAD_FAST 6 ( pairs )
66 LOAD_FAST 7 ( pairs )
68 BINARY_SUBTRACT
70 BINARY_SUBSCR
72 STORE_FAST 8 ( pairs )

11 74 LOAD_FAST 7 ( pairs )
76 LOAD_FAST 8 ( pairs )
78 LOAD_FAST 8 ( pairs )
80 BINARY_SUBTRACT
82 BINARY_SUBSCR
84 STORE_FAST 9 ( pairs )

12 86 LOAD_FAST 7 ( pairs )
88 LOAD_FAST 9 ( pairs )
90 LOAD_FAST 9 ( pairs )
92 BINARY_SUBTRACT
94 BINARY_SUBSCR
96 STORE_FAST 10 ( pairs )

13 98 LOAD_FAST 6 ( pairs )
100 LOAD_FAST 9 ( pairs )
102 LOAD_FAST 10 ( pairs )
104 BINARY_SUBTRACT
106 BINARY_SUBSCR
108 STORE_FAST 11 ( pairs )

14 110 LOAD_FAST 7 ( pairs )
112 LOAD_FAST 9 ( pairs )
114 LOAD_FAST 10 ( pairs )
116 BINARY_SUBTRACT
118 BINARY_SUBSCR
120 LOAD_FAST 11 ( pairs )
122 LOAD_FAST 9 ( pairs )
124 BINARY_SUBTRACT
126 STORE_SUBSCR
128 JUMP_ABSOLUTE 18
>> 130 POP_BLOCK
>> 132 JUMP_ABSOLUTE 18
>> 134 POP_BLOCK

15 >> 136 LOAD_FAST 2 ( min_prefix_sum )
138 RETURN_VALUE
