{"script": "# Copyright (c) 2019-present, Facebook, Inc.\n# All rights reserved.\n#\n# This source code is licensed under the license found in the\n# LICENSE file in the root directory of this source tree.\n#\ndef f_gold ( arr , n ) :\n    arr.sort ( reverse = True )\n    dimension = [ 0 , 0 ]\n    i = 0\n    j = 0\n    while ( i < n - 1 and j < 2 ) :\n        if ( arr [ i ] == arr [ i + 1 ] ) :\n            dimension [ j ] = arr [ i ]\n            j += 1\n            i += 1\n        i += 1\n    return ( dimension [ 0 ] * dimension [ 1 ] )\n\n\n#TOFILL\n\nif __name__ == '__main__':\n    param = [\n    ([1, 5, 6, 8, 9, 11, 12, 14, 16, 17, 24, 25, 36, 40, 44, 47, 49, 51, 51, 52, 67, 68, 72, 74, 81, 82, 83, 84, 92, 95, 95, 96, 99],27,),\n    ([-54, -82, -92, -32],2,),\n    ([0, 0, 0, 0, 0, 0, 0, 0, 0, 0, 0, 0, 1, 1, 1, 1, 1, 1],15,),\n    ([16, 62, 17, 15, 26, 45, 2, 17, 65, 94, 96, 30, 68, 44, 96, 60, 99],8,),\n    ([-88, -82, -78, -52, -50, -42, -34, -28, 16, 46, 54, 56, 66, 66, 74, 82, 82, 94, 98],15,),\n    ([0, 1, 0, 0, 1, 0, 0, 1, 0, 1, 0, 0, 1, 0, 1, 0, 0, 1, 0, 1, 0, 1, 1, 1, 1, 0],18,),\n    ([1, 6, 8, 8, 8, 10, 13, 14, 14, 23, 24, 25, 27, 28, 29, 30, 33, 38, 43, 44, 49, 52, 56, 58, 62, 63, 64, 65, 65, 68, 75, 85, 85, 87, 93, 96, 97],20,),\n    ([-90, -56, 16, 32, 78, -20, 76, -90, -68, -70, 54, 50, 60, -64, 78, -6, -92, 6, 16, 70],19,),\n    ([0, 0, 0, 0, 0, 0, 0, 0, 0, 0, 0, 1, 1, 1, 1, 1, 1, 1, 1, 1, 1, 1, 1, 1, 1, 1, 1, 1, 1, 1, 1, 1, 1, 1],30,),\n    ([55, 51, 90, 10, 14, 5, 57, 22, 75, 29, 7, 18, 31, 43, 84, 35, 71, 94, 4, 51, 94, 30, 94, 53, 82],22,)\n        ]\n    n_success = 0\n    for i, parameters_set in enumerate(param):\n        if f_filled(*parameters_set) == f_gold(*parameters_set):\n            n_success+=1\n    print(\"#Results: %i, %i\" % (n_success, len(param)))", "ref": "def findArea ( arr , n ) :\n    arr.sort ( reverse = True )\n    dimension = [ 0 , 0 ]\n    i = 0\n    j = 0\n    while ( i < n - 1 and j < 2 ) :\n        if ( arr [ i ] == arr [ i + 1 ] ) :\n            dimension [ j ] = arr [ i ]\n            j += 1\n            i += 1\n        i += 1\n    return ( dimension [ 0 ] * dimension [ 1 ] )\n"}
Disassembly of <code object findArea at 0x7f2b0163dc90, file "<dis>", line 1>:
2 0 LOAD_FAST 0 ( arr )
2 LOAD_METHOD 0 ( sort )
4 LOAD_CONST 1 ( True )
6 CALL_METHOD 1
8 POP_TOP

3 10 LOAD_CONST 2 ( 0 )
12 LOAD_CONST 3 ( ( '' , ) )
14 IMPORT_NAME 1 ( np )
16 IMPORT_FROM 2 ( random )
18 STORE_FAST 1 ( random )
20 POP_TOP

4 22 LOAD_CONST 1 ( True )
24 STORE_FAST 2 ( random )

5 26 SETUP_LOOP 64 ( to 92 )
28 LOAD_FAST 1 ( random )
30 LOAD_METHOD 0 ( sort )
32 LOAD_CONST 1 ( True )
34 CALL_METHOD 1
36 GET_ITER
>> 38 FOR_ITER 48 ( to 90 )
40 STORE_FAST 3 ( i )

6 42 LOAD_FAST 2 ( random )
44 LOAD_METHOD 0 ( sort )
46 LOAD_CONST 1 ( True )
48 CALL_METHOD 1
50 POP_TOP

7 52 LOAD_FAST 2 ( random )
54 LOAD_METHOD 0 ( sort )
56 LOAD_CONST 1 ( True )
58 CALL_METHOD 1
60 POP_TOP

8 62 LOAD_FAST 2 ( random )
64 LOAD_METHOD 0 ( sort )
66 LOAD_CONST 1 ( True )
68 CALL_METHOD 1
70 POP_TOP
72 JUMP_ABSOLUTE 38
>> 74 POP_BLOCK
>> 76 JUMP_ABSOLUTE 38
>> 78 POP_BLOCK

9 >> 80 LOAD_FAST 2 ( random )
82 LOAD_METHOD 0 ( sort )
84 LOAD_CONST 1 ( True )
86 CALL_METHOD 1
88 POP_TOP

10 90 LOAD_FAST 2 ( random )
92 LOAD_METHOD 0 ( sort )
94 LOAD_CONST 1 ( True )
96 CALL_METHOD 1
98 POP_TOP

11 100 LOAD_FAST 2 ( random )
102 LOAD_METHOD 0 ( sort )
104 LOAD_CONST 1 ( True )
106 CALL_METHOD 1
108 POP_TOP
110 LOAD_CONST 0 ( None )
112 RETURN_VALUE
