{"script": "# Copyright (c) 2019-present, Facebook, Inc.\n# All rights reserved.\n#\n# This source code is licensed under the license found in the\n# LICENSE file in the root directory of this source tree.\n#\nimport math\n\ndef f_gold ( C , l ) :\n    if ( l >= C ) : return C\n    eq_root = ( math.sqrt ( 1 + 8 * ( C - l ) ) - 1 ) / 2\n    return math.ceil ( eq_root ) + l\n\n\n#TOFILL\n\nif __name__ == '__main__':\n    param = [\n    (91,29,),\n    (99,55,),\n    (11,56,),\n    (23,56,),\n    (12,97,),\n    (1,64,),\n    (18,5,),\n    (14,37,),\n    (13,55,),\n    (36,99,)\n        ]\n    n_success = 0\n    for i, parameters_set in enumerate(param):\n        if f_filled(*parameters_set) == f_gold(*parameters_set):\n            n_success+=1\n    print(\"#Results: %i, %i\" % (n_success, len(param)))", "ref": "def minDaysToEmpty ( C , l ) :\n    if ( l >= C ) : return C\n    eq_root = ( math.sqrt ( 1 + 8 * ( C - l ) ) - 1 ) / 2\n    return math.ceil ( eq_root ) + l\n"}
Disassembly of <code object minDaysToEmpty at 0x7f2b01639660, file "<dis>", line 1>:
2 0 LOAD_FAST 0 ( C )
2 LOAD_FAST 1 ( l )
4 COMPARE_OP 5 ( >= )
6 POP_JUMP_IF_FALSE 22

3 8 LOAD_FAST 0 ( C )
10 LOAD_FAST 1 ( l )
12 COMPARE_OP 5 ( >= )
14 POP_JUMP_IF_FALSE 22

4 16 LOAD_FAST 0 ( C )
18 LOAD_FAST 1 ( l )
20 BINARY_SUBTRACT
22 LOAD_CONST 1 ( 2 )
24 BINARY_SUBTRACT
26 LOAD_CONST 2 ( 1 )
28 BINARY_SUBTRACT
30 LOAD_CONST 2 ( 1 )
32 BINARY_SUBTRACT
34 LOAD_CONST 2 ( 1 )
36 BINARY_SUBTRACT
38 LOAD_CONST 2 ( 1 )
40 BINARY_SUBTRACT
42 BINARY_MULTIPLY
44 BINARY_ADD
46 RETURN_VALUE

5 >> 48 LOAD_FAST 0 ( C )
50 LOAD_FAST 1 ( l )
52 BINARY_SUBTRACT
54 RETURN_VALUE
56 LOAD_CONST 0 ( None )
58 RETURN_VALUE
