{"script": "# Copyright (c) 2019-present, Facebook, Inc.\n# All rights reserved.\n#\n# This source code is licensed under the license found in the\n# LICENSE file in the root directory of this source tree.\n#\ndef f_gold ( arr , n ) :\n    max_ele = arr [ n - 1 ]\n    min_ele = arr [ 0 ]\n    for i in range ( n ) :\n        if i % 2 == 0 :\n            arr [ i ] = max_ele\n            max_ele -= 1\n        else :\n            arr [ i ] = min_ele\n            min_ele += 1\n\n\n#TOFILL\n\nif __name__ == '__main__':\n    param = [\n    ([3, 4, 8, 10, 12, 14, 14, 17, 18, 19, 20, 25, 28, 29, 30, 31, 34, 35, 37, 38, 40, 41, 42, 45, 47, 49, 54, 54, 55, 58, 58, 63, 65, 66, 66, 67, 67, 72, 74, 75, 75, 80, 82, 86, 92, 95, 96, 99],40,),\n    ([45, 42, -91, 90, -6, 49, 65, 39, -80, -65, -47, 75, 10, 80, 36, -96, 55, 72, 68, 2, -53, -6, 72, -52, -9, 80, -16, -32, 39, 25, -27, -96, -24, -27, -23, -52],23,),\n    ([0, 0, 0, 0, 0, 0, 0, 0, 0, 0, 0, 0, 0, 0, 0, 0, 0, 0, 0, 0, 1, 1, 1, 1, 1, 1, 1, 1, 1, 1, 1, 1, 1, 1, 1, 1, 1, 1, 1, 1, 1, 1],28,),\n    ([12, 84, 16],2,),\n    ([-85, -77, -70, -67, -55, -51, -49, -41, -37, -24, -18, -8, -6, 77, 87, 90],13,),\n    ([0, 0, 1, 1, 1, 1, 1, 1, 1, 0, 1, 1, 0, 0, 0],12,),\n    ([5, 8, 15, 16, 20, 22, 25, 33, 46, 48, 52, 54, 55, 57, 57, 61, 61, 66, 72, 73, 83, 87, 88, 89, 98],12,),\n    ([31, 2, -46, -86, -64, 5, -18, -33, -90, -51, 11, -35, -43, -73, 13, 33, -29, -17, -43, 20, -7, -85],13,),\n    ([0, 0, 0, 0, 0, 0, 0, 0, 0, 0, 0, 0, 0, 0, 0, 0, 0, 0, 0, 0, 0, 0, 0, 0, 0, 0, 0, 1, 1, 1, 1, 1, 1, 1, 1, 1, 1, 1, 1, 1, 1, 1, 1, 1, 1, 1, 1],31,),\n    ([20, 75, 12, 62, 18, 94, 63, 84, 25, 12],9,)\n        ]\n    filled_function_param = [\n    ([3, 4, 8, 10, 12, 14, 14, 17, 18, 19, 20, 25, 28, 29, 30, 31, 34, 35, 37, 38, 40, 41, 42, 45, 47, 49, 54, 54, 55, 58, 58, 63, 65, 66, 66, 67, 67, 72, 74, 75, 75, 80, 82, 86, 92, 95, 96, 99],40,),\n    ([45, 42, -91, 90, -6, 49, 65, 39, -80, -65, -47, 75, 10, 80, 36, -96, 55, 72, 68, 2, -53, -6, 72, -52, -9, 80, -16, -32, 39, 25, -27, -96, -24, -27, -23, -52],23,),\n    ([0, 0, 0, 0, 0, 0, 0, 0, 0, 0, 0, 0, 0, 0, 0, 0, 0, 0, 0, 0, 1, 1, 1, 1, 1, 1, 1, 1, 1, 1, 1, 1, 1, 1, 1, 1, 1, 1, 1, 1, 1, 1],28,),\n    ([12, 84, 16],2,),\n    ([-85, -77, -70, -67, -55, -51, -49, -41, -37, -24, -18, -8, -6, 77, 87, 90],13,),\n    ([0, 0, 1, 1, 1, 1, 1, 1, 1, 0, 1, 1, 0, 0, 0],12,),\n    ([5, 8, 15, 16, 20, 22, 25, 33, 46, 48, 52, 54, 55, 57, 57, 61, 61, 66, 72, 73, 83, 87, 88, 89, 98],12,),\n    ([31, 2, -46, -86, -64, 5, -18, -33, -90, -51, 11, -35, -43, -73, 13, 33, -29, -17, -43, 20, -7, -85],13,),\n    ([0, 0, 0, 0, 0, 0, 0, 0, 0, 0, 0, 0, 0, 0, 0, 0, 0, 0, 0, 0, 0, 0, 0, 0, 0, 0, 0, 1, 1, 1, 1, 1, 1, 1, 1, 1, 1, 1, 1, 1, 1, 1, 1, 1, 1, 1, 1],31,),\n    ([20, 75, 12, 62, 18, 94, 63, 84, 25, 12],9,)\n        ]\n    n_success = 0\n    for i, parameters_set in enumerate(param):\n        f_filled(*(filled_function_param[i]))\n        f_gold(*parameters_set)\n        if parameters_set == filled_function_param[i]:\n            n_success+=1\n    print(\"#Results: %i, %i\" % (n_success, len(param)))\n", "ref": "def rearrange ( arr , n ) :\n    max_ele = arr [ n - 1 ]\n    min_ele = arr [ 0 ]\n    for i in range ( n ) :\n        if i % 2 == 0 :\n            arr [ i ] = max_ele\n            max_ele -= 1\n        else :\n            arr [ i ] = min_ele\n            min_ele += 1\n"}
Disassembly of <code object rearrange at 0x7f2b0163dc90, file "<dis>", line 1>:
2 0 LOAD_FAST 0 ( arr )
2 LOAD_CONST 1 ( - 1 )
4 BINARY_SUBSCR
6 STORE_FAST 2 ( max_ele )

3 8 LOAD_FAST 0 ( arr )
10 LOAD_CONST 2 ( 0 )
12 BINARY_SUBSCR
14 STORE_FAST 3 ( min_ele )

4 16 SETUP_LOOP 64 ( to 82 )
>> 18 LOAD_FAST 1 ( n )
20 LOAD_CONST 1 ( - 1 )
22 BINARY_SUBSCR
24 STORE_FAST 4 ( temp )

5 26 SETUP_LOOP 48 ( to 80 )
28 LOAD_GLOBAL 0 ( range )
30 LOAD_FAST 1 ( n )
32 LOAD_CONST 1 ( - 1 )
34 BINARY_SUBSCR
36 CALL_FUNCTION 1
38 GET_ITER
>> 40 FOR_ITER 48 ( to 78 )
42 STORE_FAST 5 ( i )

6 44 LOAD_FAST 0 ( arr )
46 LOAD_FAST 5 ( i )
48 BINARY_SUBSCR
50 LOAD_FAST 2 ( max_ele )
52 LOAD_FAST 3 ( ele )
54 LOAD_FAST 4 ( temp )
56 BINARY_SUBSCR
58 BINARY_SUBTRACT
60 LOAD_FAST 5 ( i )
62 BINARY_SUBSCR
64 LOAD_FAST 4 ( temp )
66 LOAD_FAST 5 ( i )
68 BINARY_SUBSCR
70 BINARY_SUBTRACT
72 LOAD_FAST 5 ( i )
74 LOAD_CONST 1 ( - 1 )
76 BINARY_SUBSCR
78 BINARY_SUBTRACT
80 LOAD_FAST 5 ( i )
82 LOAD_CONST 1 ( - 1 )
84 BINARY_SUBSCR
86 BINARY_SUBTRACT
88 LOAD_FAST 5 ( i )
90 LOAD_CONST 1 ( - 1 )
92 BINARY_SUBSCR
94 BINARY_SUBTRACT
96 LOAD_FAST 5 ( i )
98 LOAD_CONST 1 ( - 1 )
100 BINARY_SUBSCR
102 BINARY_SUBTRACT
104 LOAD_FAST 5 ( i )
106 LOAD_CONST 1 ( - 1 )
108 BINARY_SUBSCR
110 BINARY_SUBTRACT
112 LOAD_FAST 5 ( i )
114 LOAD_CONST 1 ( - 1 )
116 BINARY_SUBSCR
118 BINARY_SUBTRACT
120 LOAD_FAST 5 ( i )
122 LOAD_CONST 1 ( - 1 )
124 BINARY_SUBSCR
126 BINARY_SUBTRACT
128 LOAD_FAST 5 ( i )
130 LOAD_CONST 1 ( - 1 )
132 BINARY_SUBSCR
134 BINARY_SUBTRACT
136 LOAD_FAST 5 ( i )
138 LOAD_CONST 1 ( - 1 )
140 BINARY_SUBSCR
142 BINARY_SUBTRACT
144 LOAD_FAST 5 ( i )
146 LOAD_CONST 1 ( - 1 )
148 BINARY_SUBSCR
150 BINARY_SUBTRACT
152 LOAD_FAST 5 ( i )
154 LOAD_CONST 1 ( - 1 )
156 STORE_SUBSCR

6 158 LOAD_FAST 0 ( arr )
160 LOAD_FAST 3 ( ele )
162 STORE_SUBSCR

7 164 LOAD_FAST 0 ( arr )
166 RETURN_VALUE
