{"script": "# Copyright (c) 2019-present, Facebook, Inc.\n# All rights reserved.\n#\n# This source code is licensed under the license found in the\n# LICENSE file in the root directory of this source tree.\n#\ndef f_gold ( arr , low , high , x ) :\n    if x <= arr [ low ] :\n        return low\n    i = low\n    for i in range ( high ) :\n        if arr [ i ] == x :\n            return i\n        if arr [ i ] < x and arr [ i + 1 ] >= x :\n            return i + 1\n    return - 1\n\n\n#TOFILL\n\nif __name__ == '__main__':\n    param = [\n    ([2, 3, 4, 6, 8, 9, 9, 10, 11, 16, 19, 20, 21, 21, 21, 24, 24, 25, 28, 30, 30, 30, 32, 34, 35, 39, 41, 42, 49, 52, 57, 59, 61, 62, 66, 68, 71, 73, 76, 79, 83, 84, 85, 86, 87, 87],23,37,44,),\n    ([92, 50, -84, 60, 32, -54, 84, -82, -42, -72, -64, -28, -48, 66, 92, -42, 42, -66, 52, -30, 48, 42, 36, -4, 64, 62, -16, 0, 20, 26, 78, 78, 12, -6, -30, -14, 76, 72, 70, -34, 98, 32],36,35,34,),\n    ([0, 0, 0, 0, 0, 0, 0, 0, 0, 0, 0, 1, 1, 1, 1, 1, 1],11,9,13,),\n    ([26, 68, 73, 76, 14, 19, 56, 80, 17, 7, 15, 64, 99, 98, 21, 21, 72, 12, 14, 10, 44, 82, 25, 42, 46, 86, 79, 43, 91],23,27,26,),\n    ([-90, -86, -84, -50, -30, -24, -12, -2, 8, 22, 30, 44, 58, 58, 60, 60, 62, 90],9,16,10,),\n    ([0, 0, 1, 1, 1, 1, 1, 1, 0, 1, 1, 1, 0, 1, 1, 1, 1, 1, 0, 0, 1, 1],12,15,18,),\n    ([2, 2, 29, 31, 34, 39, 48, 50, 56, 61, 66, 66, 69, 73, 88],9,12,10,),\n    ([-98, 48, -58, 8, 70, 62, 92, 84, -58, -46, -26, -92, 18, -88, 40, -12, 60, 14, 54, -64, 88, 52, -44, 88, -46, -8, 36, -22, 28, -20, -50, 58, -82, -44, -44, 54, -86, 40, 10, 0, -24, -84, -10, 62, 58, 0, -88],40,29,24,),\n    ([0, 0, 0, 0, 1, 1],5,5,5,),\n    ([56, 30, 33, 5, 67, 35, 22, 54, 36, 55, 94, 89, 40, 65, 29, 76, 17, 14, 14, 49, 40, 44, 35, 69, 63, 2, 81, 78, 19, 67, 12, 14, 68, 30, 82, 85, 12, 2, 94, 33, 85, 75, 97, 31, 69, 31, 85, 26],46,47,47,)\n        ]\n    n_success = 0\n    for i, parameters_set in enumerate(param):\n        if f_filled(*parameters_set) == f_gold(*parameters_set):\n            n_success+=1\n    print(\"#Results: %i, %i\" % (n_success, len(param)))", "ref": "def ceilSearch ( arr , low , high , x ) :\n    if x <= arr [ low ] :\n        return low\n    i = low\n    for i in range ( high ) :\n        if arr [ i ] == x :\n            return i\n        if arr [ i ] < x and arr [ i + 1 ] >= x :\n            return i + 1\n    return - 1\n"}
Disassembly of <code object ceilSearch at 0x7f816a673a50, file "<dis>", line 70>:
71 0 LOAD_FAST 0 ( arr )
2 LOAD_FAST 1 ( low )
4 BINARY_MULTIPLY
6 STORE_FAST 2 ( high )

72 8 LOAD_FAST 2 ( high )
10 LOAD_CONST 1 ( 1 )
12 INPLACE_ADD
14 STORE_FAST 2 ( high )

73 16 LOAD_FAST 2 ( high )
18 LOAD_CONST 2 ( 2 )
20 INPLACE_ADD
22 STORE_FAST 2 ( high )

74 24 LOAD_FAST 2 ( high )
26 LOAD_CONST 3 ( 1 )
28 INPLACE_ADD
30 STORE_FAST 2 ( high )

75 32 LOAD_FAST 2 ( high )
34 LOAD_CONST 4 ( 3 )
36 INPLACE_ADD
38 STORE_FAST 2 ( high )

76 40 LOAD_FAST 2 ( high )
42 LOAD_CONST 5 ( 1 )
44 INPLACE_ADD
46 STORE_FAST 2 ( high )

77 48 LOAD_FAST 2 ( high )
50 LOAD_CONST 6 ( 2 )
52 INPLACE_ADD
54 STORE_FAST 2 ( high )

78 56 LOAD_FAST 2 ( high )
58 LOAD_CONST 7 ( 2 )
60 INPLACE_ADD
62 STORE_FAST 2 ( high )

79 64 LOAD_FAST 2 ( high )
66 LOAD_CONST 8 ( 2 )
68 INPLACE_ADD
70 STORE_FAST 2 ( high )

80 72 LOAD_FAST 2 ( high )
74 LOAD_CONST 9 ( 2 )
76 INPLACE_ADD
78 STORE_FAST 2 ( high )
80 STORE_FAST 3 ( high )

81 82 LOAD_FAST 2 ( high )
84 LOAD_FAST 3 ( high )
86 LOAD_CONST 10 ( 2 )
88 INPLACE_ADD
90 STORE_FAST 2 ( high )

82 92 LOAD_FAST 2 ( high )
94 LOAD_CONST 11 ( 1 )
96 INPLACE_ADD
98 STORE_FAST 2 ( high )

83 100 LOAD_FAST 2 ( high )
102 LOAD_CONST 12 ( 2 )
104 INPLACE_ADD
106 STORE_FAST 2 ( high )

84 108 LOAD_FAST 2 ( high )
110 LOAD_CONST 13 ( 1 )
112 INPLACE_ADD
114 STORE_FAST 2 ( high )

85 116 LOAD_FAST 2 ( high )
118 LOAD_FAST 2 ( high )
120 INPLACE_ADD
122 STORE_FAST 2 ( high )

86 124 LOAD_FAST 2 ( high )
126 LOAD_FAST 2 ( high )
128 INPLACE_ADD
130 STORE_FAST 2 ( high )

87 132 LOAD_FAST 2 ( high )
134 LOAD_FAST 2 ( high )
136 INPLACE_ADD
138 STORE_FAST 2 ( high )

88 140 LOAD_FAST 2 ( high )
142 RETURN_VALUE

