{"script": "# Copyright (c) 2019-present, Facebook, Inc.\n# All rights reserved.\n#\n# This source code is licensed under the license found in the\n# LICENSE file in the root directory of this source tree.\n#\ndef f_gold ( a , b , k , n1 , n2 ) :\n    s = set ( )\n    for i in range ( n2 ) :\n        s.add ( b [ i ] )\n    missing = 0\n    for i in range ( n1 ) :\n        if a [ i ] not in s :\n            missing += 1\n        if missing == k :\n            return a [ i ]\n    return - 1\n\n\n#TOFILL\n\nif __name__ == '__main__':\n    param = [\n    ([2, 9, 9, 13, 38, 41, 50, 59, 64, 64, 72, 78, 79, 80, 84, 92, 94, 98, 99],[5, 9, 11, 21, 24, 27, 30, 35, 38, 39, 40, 45, 48, 48, 51, 58, 61, 91, 92],11,9,18,),\n    ([-54, -80, -62, 98, -68, 42, 98, 80, -8, -6, 26, 0, -60, -24, -74, -48, 4, -54, 20, 32, 42, 68, -50, 58, -50, 96, -34, 22, 56, -60, -10, -18, 80, 20, -50],[90, -86, -82, 92, -42, -34, 10, -28, -78, 8, 66, 96, -16, -22, -68, -36, -72, 84, -54, -44, -80, -30, 64, 10, -60, -90, 22, 54, -88, 74, -56, 22, -24, -52, 82],24,24,21,),\n    ([0, 0, 0, 0, 0, 0, 0, 1, 1, 1, 1, 1, 1, 1, 1, 1],[0, 0, 0, 0, 0, 0, 0, 0, 0, 1, 1, 1, 1, 1, 1, 1],15,15,11,),\n    ([85, 44, 60, 86, 26, 22, 95, 47, 43, 24, 30, 37, 22, 33, 6, 56],[66, 76, 38, 91, 57, 50, 12, 21, 90, 17, 18, 78, 23, 12, 90, 81],12,14,10,),\n    ([-32, -18, 2, 54, 72, 92, 94],[-76, -68, -34, -24, 8, 12, 32],6,3,5,),\n    ([1, 0, 1, 0, 1, 0, 1, 0, 1, 0, 1, 1, 1, 0, 0, 0, 1, 0, 1, 0, 1, 0, 1, 0, 1, 0, 0, 0, 1, 1, 0, 1, 1, 1, 1, 1, 1, 0, 0, 0, 1, 0, 1, 1, 1, 0, 0],[0, 0, 1, 1, 1, 0, 0, 0, 0, 1, 0, 0, 0, 0, 1, 1, 0, 0, 0, 0, 0, 1, 1, 0, 1, 0, 1, 1, 0, 1, 0, 0, 1, 1, 0, 1, 0, 1, 1, 0, 1, 1, 0, 1, 0, 1, 0],29,29,37,),\n    ([3, 9, 13, 14, 16, 19, 20, 21, 23, 26, 27, 27, 28, 29, 31, 36, 37, 38, 41, 42, 45, 46, 52, 56, 63, 65, 70, 70, 72, 72, 76, 77, 78, 78, 79, 82, 83, 86, 87, 87, 90, 93, 93, 94, 96, 96, 97, 98],[2, 5, 6, 7, 9, 11, 11, 13, 17, 18, 20, 20, 26, 27, 35, 35, 36, 37, 41, 42, 45, 46, 48, 49, 50, 50, 54, 54, 56, 60, 62, 63, 65, 67, 68, 68, 70, 72, 74, 74, 78, 79, 80, 80, 86, 89, 97, 99],27,39,28,),\n    ([-82, -62],[48, 32],1,1,1,),\n    ([0, 0, 0, 0, 0, 0, 0, 1, 1, 1, 1, 1, 1, 1, 1],[0, 0, 0, 0, 0, 0, 1, 1, 1, 1, 1, 1, 1, 1, 1],10,14,12,),\n    ([26, 5, 60, 53, 35],[41, 80, 35, 14, 47],3,2,3,)\n        ]\n    n_success = 0\n    for i, parameters_set in enumerate(param):\n        if f_filled(*parameters_set) == f_gold(*parameters_set):\n            n_success+=1\n    print(\"#Results: %i, %i\" % (n_success, len(param)))", "ref": "def find ( a , b , k , n1 , n2 ) :\n    s = set ( )\n    for i in range ( n2 ) :\n        s.add ( b [ i ] )\n    missing = 0\n    for i in range ( n1 ) :\n        if a [ i ] not in s :\n            missing += 1\n        if missing == k :\n            return a [ i ]\n    return - 1\n"}
Disassembly of <code object find at 0x7f816a683d20, file "<dis>", line n2>:
n2 0 LOAD_GLOBAL 0 ( set )
2 LOAD_FAST 0 ( a )
4 CALL_FUNCTION 1
6 STORE_FAST 1 ( b )

n2 8 LOAD_FAST 1 ( b )
10 LOAD_FAST 1 ( b )
12 LOAD_FAST 2 ( b )
14 LOAD_FAST 3 ( b )
16 LOAD_FAST 4 ( b )
18 LOAD_FAST 5 ( b )
20 LOAD_FAST 6 ( b )
22 LOAD_FAST 7 ( b )
24 LOAD_FAST 8 ( b )
26 LOAD_FAST 9 ( b )
28 LOAD_FAST 10 ( b )
30 LOAD_FAST 11 ( b )
32 LOAD_FAST 12 ( b )
34 LOAD_FAST 13 ( b )
36 LOAD_FAST 14 ( b )
38 LOAD_FAST 15 ( b )
40 LOAD_FAST 14 ( b )
42 LOAD_FAST 16 ( b )
44 LOAD_FAST 15 ( b )
46 LOAD_FAST 16 ( b )
48 LOAD_FAST 17 ( b )
50 LOAD_FAST 18 ( b )
52 LOAD_FAST 19 ( b )
54 LOAD_FAST 18 ( b )
56 LOAD_FAST 19 ( b )
58 LOAD_FAST 20 ( b )
60 LOAD_FAST 21 ( b )
62 LOAD_FAST 22 ( b )
64 LOAD_FAST 21 ( b )
66 LOAD_FAST 22 ( b )
68 LOAD_FAST 21 ( b )
70 LOAD_FAST 22 ( b )
72 LOAD_FAST 21 ( b )
74 LOAD_FAST 22 ( b )
76 LOAD_FAST 21 ( b )
78 LOAD_FAST 22 ( b )
80 LOAD_FAST 21 ( b )
82 LOAD_FAST 22 ( b )
84 LOAD_FAST 21 ( b )
86 LOAD_FAST 22 ( b )
88 LOAD_FAST 21 ( b )
90 LOAD_FAST 22 ( b )
92 LOAD_FAST 21 ( b )
94 LOAD_FAST 22 ( b )
96 LOAD_FAST 21 ( b )
98 LOAD_FAST 22 ( b )
100 LOAD_FAST 21 ( b )
102 LOAD_FAST 22 ( b )
104 LOAD_FAST 21 ( b )
106 LOAD_FAST 22 ( b )
108 LOAD_FAST 21 ( b )
110 LOAD_FAST 22 ( b )
112 LOAD_FAST 21 ( b )
114 LOAD_FAST 22 ( b )
116 LOAD_FAST 21 ( b )
118 LOAD_FAST 22 ( b )
120 LOAD_FAST 21 ( b )
122 LOAD_FAST 22 ( b )
124 BUILD_TUPLE 21
126 CALL_FUNCTION 5
128 RETURN_VALUE

