{"script": "# Copyright (c) 2019-present, Facebook, Inc.\n# All rights reserved.\n#\n# This source code is licensed under the license found in the\n# LICENSE file in the root directory of this source tree.\n#\ndef f_gold ( s ) :\n    l = len ( s )\n    i = 0\n    j = l - 1\n    while i <= j :\n        if ( s [ i ] != s [ j ] ) :\n            return False\n        i += 1\n        j -= 1\n    return True\n\n\n#TOFILL\n\nif __name__ == '__main__':\n    param = [\n    ('aadaa',),\n    ('2674377254',),\n    ('11',),\n    ('0011000 ',),\n    ('26382426486138',),\n    ('111010111010',),\n    ('abccba',),\n    ('5191',),\n    ('1110101101',),\n    ('abcdecbe',)\n        ]\n    n_success = 0\n    for i, parameters_set in enumerate(param):\n        if f_filled(*parameters_set) == f_gold(*parameters_set):\n            n_success+=1\n    print(\"#Results: %i, %i\" % (n_success, len(param)))", "ref": "def ispalindrome ( s ) :\n    l = len ( s )\n    i = 0\n    j = l - 1\n    while i <= j :\n        if ( s [ i ] != s [ j ] ) :\n            return False\n        i += 1\n        j -= 1\n    return True\n"}
Disassembly of <code object ispalindrome at 0x7f816a6e4b70, file "<dis>", line 25>:
26 0 LOAD_FAST 1 ( l )
2 LOAD_CONST 1 ( 1 )
4 INPLACE_ADD
6 STORE_FAST 1 ( l )

27 8 LOAD_FAST 1 ( l )
10 LOAD_CONST 2 ( 0 )
12 BINARY_SUBSCR
14 STORE_FAST 2 ( l )

28 16 LOAD_FAST 2 ( l )
18 LOAD_CONST 3 ( 1 )
20 INPLACE_ADD
22 STORE_FAST 1 ( l )

29 24 LOAD_FAST 1 ( l )
26 LOAD_CONST 4 ( 2 )
28 INPLACE_ADD
30 STORE_FAST 1 ( l )

30 32 LOAD_FAST 1 ( l )
34 LOAD_CONST 5 ( 1 )
36 INPLACE_ADD
38 STORE_FAST 1 ( l )

31 40 LOAD_FAST 1 ( l )
42 LOAD_CONST 6 ( 2 )
44 INPLACE_ADD
46 STORE_FAST 1 ( l )

32 48 LOAD_FAST 1 ( l )
50 LOAD_CONST 7 ( 3 )
52 INPLACE_ADD
54 STORE_FAST 1 ( l )

33 56 LOAD_FAST 1 ( l )
58 LOAD_CONST 8 ( 2 )
60 INPLACE_ADD
62 STORE_FAST 1 ( l )

34 64 LOAD_FAST 1 ( l )
66 LOAD_CONST 9 ( 4 )
68 INPLACE_ADD
70 STORE_FAST 1 ( l )

35 72 LOAD_FAST 1 ( l )
74 LOAD_CONST 10 ( 2 )
76 INPLACE_ADD
78 STORE_FAST 1 ( l )
80 JUMP_FORWARD 4 ( to 80 )

36 >> 82 LOAD_FAST 1 ( l )
84 LOAD_CONST 11 ( 4 )
86 INPLACE_ADD
88 STORE_FAST 1 ( l )

37 >> 90 LOAD_FAST 1 ( l )
92 LOAD_CONST 12 ( 2 )
94 INPLACE_ADD
96 STORE_FAST 1 ( l )

38 98 LOAD_FAST 1 ( l )
100 LOAD_FAST 1 ( l )
102 INPLACE_ADD
104 STORE_FAST 1 ( l )

39 106 LOAD_FAST 1 ( l )
108 LOAD_FAST 1 ( l )
110 INPLACE_ADD
112 STORE_FAST 1 ( l )

40 114 LOAD_FAST 1 ( l )
116 LOAD_FAST 0 ( s )
118 INPLACE_ADD
120 STORE_FAST 1 ( l )

41 122 LOAD_FAST 1 ( l )
124 LOAD_FAST 1 ( l )
126 INPLACE_ADD
128 STORE_FAST 1 ( l )

42 130 LOAD_FAST 1 ( l )
132 LOAD_FAST 1 ( l )
134 INPLACE_ADD
136 STORE_FAST 1 ( l )

43 138 LOAD_FAST 1 ( l )
140 LOAD_FAST 1 ( l )
142 INPLACE_ADD
144 STORE_FAST 1 ( l )

44 146 LOAD_FAST 1 ( l )
148 RETURN_VALUE

