{"script": "# Copyright (c) 2019-present, Facebook, Inc.\n# All rights reserved.\n#\n# This source code is licensed under the license found in the\n# LICENSE file in the root directory of this source tree.\n#\ndef f_gold ( n ) :\n    num = n ;\n    dec_value = 0 ;\n    base1 = 1 ;\n    len1 = len ( num ) ;\n    for i in range ( len1 - 1 , - 1 , - 1 ) :\n        if ( num [ i ] == '1' ) :\n            dec_value += base1 ;\n        base1 = base1 * 2 ;\n    return dec_value ;\n\n\n#TOFILL\n\nif __name__ == '__main__':\n    param = [\n    ('uEmIAgF',),\n    ('753310137',),\n    ('010011010',),\n    ('kNi',),\n    ('04562016903312',),\n    ('000111101',),\n    ('bk',),\n    ('9',),\n    ('1',),\n    ('XxT nXLlk',)\n        ]\n    n_success = 0\n    for i, parameters_set in enumerate(param):\n        if f_filled(*parameters_set) == f_gold(*parameters_set):\n            n_success+=1\n    print(\"#Results: %i, %i\" % (n_success, len(param)))", "ref": "def binaryToDecimal ( n ) :\n    num = n ;\n    dec_value = 0 ;\n    base1 = 1 ;\n    len1 = len ( num ) ;\n    for i in range ( len1 - 1 , - 1 , - 1 ) :\n        if ( num [ i ] == '1' ) :\n            dec_value += base1 ;\n        base1 = base1 * 2 ;\n    return dec_value ;\n"}
Disassembly of <code object binaryToDecimal at 0x7f816a6e4b70, file "<dis>", line 25>:
26 0 LOAD_FAST 1 ( num )
2 LOAD_CONST 1 ( 0 )
4 BINARY_SUBSCR
6 STORE_FAST 2 ( num )

27 8 LOAD_FAST 2 ( num )
10 LOAD_CONST 1 ( 0 )
12 BINARY_SUBSCR
14 STORE_FAST 3 ( num )

28 16 LOAD_FAST 3 ( num )
18 LOAD_CONST 1 ( 0 )
20 BINARY_SUBSCR
22 STORE_FAST 4 ( num )

29 24 LOAD_FAST 4 ( num )
26 LOAD_CONST 2 ( 1 )
28 BINARY_SUBSCR
30 LOAD_CONST 3 ( '%d %d %d' )
32 LOAD_FAST 4 ( num )
34 BINARY_MODULO
36 LOAD_CONST 4 ( '%d %d %d' )
38 LOAD_FAST 4 ( num )
40 BINARY_MODULO
42 LOAD_CONST 5 ( '%d %d %d' )
44 LOAD_FAST 4 ( num )
46 BINARY_MODULO
48 BINARY_MODULO
50 LOAD_CONST 6 ( '%d %d %d' )
52 LOAD_FAST 4 ( num )
54 BINARY_MODULO
56 LOAD_CONST 7 ( '%d %d %d %d' )
58 LOAD_FAST 4 ( num )
60 BINARY_MODULO
62 BINARY_MODULO
64 LOAD_CONST 8 ( '%d %d %d %d' )
66 LOAD_FAST 4 ( num )
68 BINARY_MODULO
70 BINARY_MODULO
72 LOAD_CONST 9 ( '%d %d %d %d' )
74 LOAD_FAST 4 ( num )
76 BINARY_MODULO
78 LOAD_CONST 10 ( '%d %d %d' )
80 LOAD_FAST 4 ( num )
82 BINARY_MODULO
84 BINARY_MODULO
86 LOAD_CONST 11 ( '%d %d %d' )
88 LOAD_FAST 4 ( num )
90 BINARY_MODULO
92 LOAD_CONST 12 ( '%d %d %d' )
94 LOAD_FAST 4 ( num )
96 BINARY_MODULO
98 BUILD_TUPLE 2
100 BINARY_MODULO
102 RETURN_VALUE

