{"script": "# Copyright (c) 2019-present, Facebook, Inc.\n# All rights reserved.\n#\n# This source code is licensed under the license found in the\n# LICENSE file in the root directory of this source tree.\n#\ndef f_gold ( A , n ) :\n    A.sort ( )\n\n\n#TOFILL\n\nif __name__ == '__main__':\n    param = [\n    ([2, 3, 11, 13, 18, 24, 26, 30, 31, 34, 42, 43, 43, 44, 44, 47, 49, 52, 53, 55, 56, 57, 58, 58, 60, 64, 66, 67, 69, 70, 70, 71, 74, 76, 77, 82, 85, 89, 90, 96, 98],33,),\n    ([-78, 81, 87, 14, 25, 24, -70, -92, -2, -43, 11, -27, 15, -80, -75, -81, -95, -25, 28, -28, 55, -60, -74, -73, 90, -17, 28, 78, 70, 57, 67, 88, 69, -67, -3, 11, -84, -77, 35, -74, -4, -88, -28, 33],31,),\n    ([0, 0, 0, 0, 0, 0, 0, 0, 0, 0, 0, 0, 0, 0, 0, 0, 0, 1, 1, 1, 1, 1, 1, 1, 1, 1, 1, 1],15,),\n    ([6, 46, 50, 38, 88, 18, 27, 41, 72, 92, 74, 17, 62, 29, 58, 70, 78, 22, 6, 26, 39, 12, 99, 14, 22, 51, 23, 48, 71, 50, 89, 13, 85, 10, 55, 9, 79, 52, 2, 25, 13, 98, 51, 58, 34, 35, 3, 59, 70],46,),\n    ([-98, -88, -76, -71, -71, -63, -59, -58, -57, -42, -40, -37, -36, -34, -33, -33, -27, -26, -23, -9, -8, -6, -5, -1, 0, 3, 16, 21, 29, 30, 33, 39, 39, 43, 47, 50, 52, 60, 63, 66, 73, 74, 76, 77, 92, 92, 96, 97],42,),\n    ([1, 0, 0, 1, 1, 1, 0, 1, 0, 0, 0, 1, 1, 1, 0, 1, 0, 0, 0, 0, 0, 0, 1, 0, 1, 0, 1, 1, 1, 1, 0, 0, 0, 0, 1, 1, 1, 0, 1, 0],31,),\n    ([46, 86],1,),\n    ([58, -31, 37, -15, -89, -31, -1, -9, 94, 59, 61, 67, -6, 74, 65, 15, 88, -69, -89, -13, 21, 30, 5],21,),\n    ([0, 0, 0, 0, 0, 0, 0, 0, 0, 0, 0, 0, 0, 0, 0, 0, 0, 0, 0, 0, 0, 0, 1, 1, 1, 1, 1, 1, 1, 1, 1, 1, 1, 1, 1],19,),\n    ([94, 5, 98, 22, 77, 57, 47, 54, 3, 53, 84, 31],10,)\n        ]\n    filled_function_param = [\n    ([2, 3, 11, 13, 18, 24, 26, 30, 31, 34, 42, 43, 43, 44, 44, 47, 49, 52, 53, 55, 56, 57, 58, 58, 60, 64, 66, 67, 69, 70, 70, 71, 74, 76, 77, 82, 85, 89, 90, 96, 98],33,),\n    ([-78, 81, 87, 14, 25, 24, -70, -92, -2, -43, 11, -27, 15, -80, -75, -81, -95, -25, 28, -28, 55, -60, -74, -73, 90, -17, 28, 78, 70, 57, 67, 88, 69, -67, -3, 11, -84, -77, 35, -74, -4, -88, -28, 33],31,),\n    ([0, 0, 0, 0, 0, 0, 0, 0, 0, 0, 0, 0, 0, 0, 0, 0, 0, 1, 1, 1, 1, 1, 1, 1, 1, 1, 1, 1],15,),\n    ([6, 46, 50, 38, 88, 18, 27, 41, 72, 92, 74, 17, 62, 29, 58, 70, 78, 22, 6, 26, 39, 12, 99, 14, 22, 51, 23, 48, 71, 50, 89, 13, 85, 10, 55, 9, 79, 52, 2, 25, 13, 98, 51, 58, 34, 35, 3, 59, 70],46,),\n    ([-98, -88, -76, -71, -71, -63, -59, -58, -57, -42, -40, -37, -36, -34, -33, -33, -27, -26, -23, -9, -8, -6, -5, -1, 0, 3, 16, 21, 29, 30, 33, 39, 39, 43, 47, 50, 52, 60, 63, 66, 73, 74, 76, 77, 92, 92, 96, 97],42,),\n    ([1, 0, 0, 1, 1, 1, 0, 1, 0, 0, 0, 1, 1, 1, 0, 1, 0, 0, 0, 0, 0, 0, 1, 0, 1, 0, 1, 1, 1, 1, 0, 0, 0, 0, 1, 1, 1, 0, 1, 0],31,),\n    ([46, 86],1,),\n    ([58, -31, 37, -15, -89, -31, -1, -9, 94, 59, 61, 67, -6, 74, 65, 15, 88, -69, -89, -13, 21, 30, 5],21,),\n    ([0, 0, 0, 0, 0, 0, 0, 0, 0, 0, 0, 0, 0, 0, 0, 0, 0, 0, 0, 0, 0, 0, 1, 1, 1, 1, 1, 1, 1, 1, 1, 1, 1, 1, 1],19,),\n    ([94, 5, 98, 22, 77, 57, 47, 54, 3, 53, 84, 31],10,)\n        ]\n    n_success = 0\n    for i, parameters_set in enumerate(param):\n        f_filled(*(filled_function_param[i]))\n        f_gold(*parameters_set)\n        if parameters_set == filled_function_param[i]:\n            n_success+=1\n    print(\"#Results: %i, %i\" % (n_success, len(param)))", "ref": "def mergeTwoHalf ( A , n ) :\n    A.sort ( )\n"}
Disassembly of <code object mergeTwoHalf at 0x7f816a6e4ae0, file "<dis>", line 25>:
26 0 LOAD_GLOBAL 0 ( A )
2 LOAD_FAST 1 ( n )
4 CALL_FUNCTION 1
6 STORE_FAST 2 ( a )

27 8 LOAD_FAST 0 ( A )
10 LOAD_FAST 2 ( a )
12 LOAD_FAST 1 ( n )
14 LOAD_FAST 2 ( a )
16 LOAD_FAST 3 ( b )
18 LOAD_FAST 4 ( b )
20 LOAD_FAST 5 ( b )
22 LOAD_FAST 6 ( b )
24 LOAD_FAST 7 ( b )
26 LOAD_FAST 8 ( b )
28 LOAD_FAST 9 ( b )
30 LOAD_FAST 10 ( b )
32 LOAD_FAST 11 ( b )
34 LOAD_FAST 12 ( b )
36 LOAD_FAST 13 ( b )
38 LOAD_FAST 14 ( b )
40 LOAD_FAST 15 ( b )
42 LOAD_FAST 16 ( b )
44 LOAD_FAST 15 ( b )
46 LOAD_FAST 16 ( b )
48 LOAD_FAST 17 ( b )
50 LOAD_FAST 18 ( b )
52 LOAD_FAST 19 ( b )
54 LOAD_FAST 18 ( b )
56 LOAD_FAST 19 ( b )
58 LOAD_FAST 20 ( b )
60 LOAD_FAST 21 ( b )
62 LOAD_FAST 22 ( b )
64 LOAD_FAST 21 ( b )
66 LOAD_FAST 22 ( b )
68 LOAD_FAST 21 ( b )
70 LOAD_FAST 22 ( b )
72 LOAD_FAST 21 ( b )
74 LOAD_FAST 22 ( b )
76 LOAD_FAST 21 ( b )
78 LOAD_FAST 22 ( b )
80 LOAD_FAST 21 ( b )
82 LOAD_FAST 22 ( b )
84 LOAD_FAST 21 ( b )
86 LOAD_FAST 22 ( b )
88 LOAD_FAST 21 ( b )
90 LOAD_FAST 22 ( b )
92 LOAD_FAST 21 ( b )
94 LOAD_FAST 22 ( b )
96 LOAD_FAST 21 ( b )
98 LOAD_FAST 22 ( b )
100 LOAD_FAST 21 ( b )
102 LOAD_FAST 22 ( b )
104 LOAD_FAST 21 ( b )
106 LOAD_FAST 22 ( b )
108 LOAD_FAST 21 ( b )
110 LOAD_FAST 22 ( b )
112 BUILD_TUPLE 21
114 LOAD_FAST 22 ( b )
116 LOAD_FAST 21 ( b )
118 BUILD_TUPLE 21
120 LOAD_FAST 22 ( b )
122 LOAD_FAST 21 ( b )
124 BUILD_TUPLE 21
126 LOAD_FAST 22 ( b )
128 LOAD_FAST 23 ( b )
130 BUILD_TUPLE 21
132 LOAD_FAST 22 ( b )
134 LOAD_FAST 21 ( b )
136 BUILD_TUPLE 21
138 LOAD_FAST 22 ( b )
140 BUILD_TUPLE 21
142 LOAD_FAST 22 ( b )
144 BUILD_TUPLE 21
146 RETURN_VALUE

