{"script": "# Copyright (c) 2019-present, Facebook, Inc.\n# All rights reserved.\n#\n# This source code is licensed under the license found in the\n# LICENSE file in the root directory of this source tree.\n#\ndef f_gold ( A , N , M ) :\n    sum = 0\n    ans = 0\n    for i in range ( 0 , N ) :\n        for j in range ( i + 1 , N ) :\n            for k in range ( j + 1 , N ) :\n                sum = A [ i ] + A [ j ] + A [ k ]\n                if ( sum % M == 0 ) :\n                    ans = ans + 1\n    return ans\n\n\n#TOFILL\n\nif __name__ == '__main__':\n    param = [\n    ([14, 35, 56, 70, 88],3,4,),\n    ([-50, -92, 16, -68, -36],3,4,),\n    ([0, 0, 0, 1, 1, 1],4,5,),\n    ([76, 43, 22, 41, 49, 99, 25, 40, 3, 45, 60, 16, 83, 62, 26, 93, 64, 73, 72, 53, 6, 32, 35, 67, 17],14,21,),\n    ([-90, -86, -86, -66, -50, -48, -44, -42, -42, -38, -24, -22, -20, -18, -8, 8, 24, 28, 34, 48, 60, 62, 66, 68, 74, 76, 80, 82, 88],24,20,),\n    ([1, 1, 1, 0, 0, 1, 0, 1, 0, 1, 1, 0, 0, 1, 1, 0, 1, 0, 0, 1, 1, 0, 1, 1, 0, 0, 0, 1, 1, 0, 1, 1, 1, 0, 1, 1, 0],24,30,),\n    ([4, 5, 8, 9, 10, 12, 13, 16, 17, 18, 21, 21, 25, 27, 28, 30, 36, 36, 54, 55, 56, 57, 60, 62, 67, 67, 68, 71, 72, 72, 73, 73, 77, 77, 83, 86, 86, 86, 87, 89, 92, 92, 96, 97, 97, 98],24,23,),\n    ([-64, 52, -32, 38, 8, -62, -56, 20, 72, -12, 32, 44],6,6,),\n    ([0, 0, 0, 0, 0, 0, 0, 0, 0, 0, 0, 0, 1, 1, 1, 1, 1, 1, 1, 1, 1, 1, 1, 1, 1],12,15,),\n    ([77, 68, 45, 6, 27, 19, 29, 95, 21, 2, 39, 48, 72, 67, 49, 45, 1, 16, 56, 78, 25, 22, 27, 40, 31, 34, 26, 35, 12],25,25,)\n        ]\n    n_success = 0\n    for i, parameters_set in enumerate(param):\n        if f_filled(*parameters_set) == f_gold(*parameters_set):\n            n_success+=1\n    print(\"#Results: %i, %i\" % (n_success, len(param)))", "ref": "def coutSubSeq ( A , N , M ) :\n    sum = 0\n    ans = 0\n    for i in range ( 0 , N ) :\n        for j in range ( i + 1 , N ) :\n            for k in range ( j + 1 , N ) :\n                sum = A [ i ] + A [ j ] + A [ k ]\n                if ( sum % M == 0 ) :\n                    ans = ans + 1\n    return ans\n"}
Disassembly of <code object coutSubSeq at 0x7f816a677930, file "<dis>", line 64>:
65 0 LOAD_GLOBAL 0 ( sum )
2 LOAD_FAST 0 ( A )
4 LOAD_FAST 1 ( N )
6 CALL_FUNCTION 2
8 STORE_FAST 2 ( a )

66 10 LOAD_FAST 2 ( a )
12 LOAD_FAST 0 ( A )
14 LOAD_FAST 1 ( N )
16 BINARY_MULTIPLY
18 LOAD_FAST 2 ( a )
20 BINARY_MULTIPLY
22 LOAD_FAST 0 ( A )
24 BINARY_MULTIPLY
26 LOAD_FAST 0 ( A )
28 BINARY_MULTIPLY
30 LOAD_FAST 2 ( a )
32 BINARY_MULTIPLY
34 BINARY_ADD
36 LOAD_FAST 0 ( A )
38 BINARY_MULTIPLY
40 BINARY_ADD
42 LOAD_FAST 0 ( A )
44 BINARY_MULTIPLY
46 BINARY_ADD
48 LOAD_FAST 2 ( a )
50 BINARY_MULTIPLY
52 BINARY_ADD
54 RETURN_VALUE

