{"script": "# Copyright (c) 2019-present, Facebook, Inc.\n# All rights reserved.\n#\n# This source code is licensed under the license found in the\n# LICENSE file in the root directory of this source tree.\n#\ndef f_gold ( n ) :\n    return ( n != 0 and ( ( n & ( n - 1 ) ) == 0 ) and not ( n & 0xAAAAAAAA ) ) ;\n\n\n#TOFILL\n\nif __name__ == '__main__':\n    param = [\n    (1,),\n    (4,),\n    (64,),\n    (-64,),\n    (128,),\n    (1024,),\n    (97,),\n    (86,),\n    (14,),\n    (99,)\n        ]\n    n_success = 0\n    for i, parameters_set in enumerate(param):\n        if f_filled(*parameters_set) == f_gold(*parameters_set):\n            n_success+=1\n    print(\"#Results: %i, %i\" % (n_success, len(param)))", "ref": "def isPowerOfFour ( n ) :\n    return ( n != 0 and ( ( n & ( n - 1 ) ) == 0 ) and not ( n & 0xAAAAAAAA ) ) ;\n"}
Disassembly of <code object isPowerOfFour at 0x7f2b0163dc90, file "<dis>", line 1>:
2 0 LOAD_FAST 0 ( n )
2 LOAD_CONST 1 ( 0 )
4 COMPARE_OP 3 ( != )
6 JUMP_IF_FALSE_OR_POP 30
8 LOAD_FAST 0 ( n )
10 LOAD_FAST 0 ( n )
12 LOAD_CONST 2 ( 1 )
14 BINARY_SUBTRACT
16 BINARY_AND
18 LOAD_CONST 1 ( 0 )
20 COMPARE_OP 2 ( == )
22 JUMP_IF_FALSE_OR_POP 30
24 LOAD_FAST 0 ( n )
26 LOAD_CONST 3 ( 4AAAAAAAA )
28 BINARY_AND
>> 30 RETURN_VALUE
