{"script": "# Copyright (c) 2019-present, Facebook, Inc.\n# All rights reserved.\n#\n# This source code is licensed under the license found in the\n# LICENSE file in the root directory of this source tree.\n#\ndef f_gold ( s1 , s2 , index ) :\n    s2 [ index ] = s1 [ index ] ;\n    if ( index == len ( s1 ) - 1 ) :\n        return ;\n    f_gold ( s1 , s2 , index + 1 ) ;\n\n\n#TOFILL\n\nif __name__ == '__main__':\n    param = [\n    (['v'],['Z'],0,),\n    (['6', '8', '3', '3', '5', '2', '5', '6', '9', '9', '2', '6', '2', '1', '9', '3', '7'],['8', '6', '0', '2', '8', '0', '8', '7', '0', '5', '4', '5', '9', '4', '5', '4', '4'],11,),\n    (['0', '0', '0', '0', '0', '0', '0', '0', '0', '0', '0', '0', '0', '0', '1', '1', '1', '1', '1', '1', '1', '1', '1', '1', '1', '1', '1', '1', '1', '1', '1', '1', '1', '1', '1'],['0', '0', '0', '0', '0', '0', '0', '0', '0', '0', '0', '0', '0', '0', '0', '0', '0', '1', '1', '1', '1', '1', '1', '1', '1', '1', '1', '1', '1', '1', '1', '1', '1', '1', '1'],34,),\n    (['e', 'G', 'a', 'r', 'F', 'U', 'W', 'k', 'u', 'z', 'y', 'v', 'A', 'W', 'm', 'G', 'H', 'O', 'I', 'a', 'u', 'V', 'f', 'B', 'q', 'e', 'E', 'e', 'L', 'c', ' ', 'w', 'K', ' ', 'K', 'j', 'j', 's', 'q', 'u', 'n', 'i', 'T', 'a', 'Y'],['S', 'm', 'd', 'a', 'W', 'N', 'F', 'H', 'B', 'E', 'h', 'M', 'z', 'H', 'c', 'X', 'l', 'a', 'R', 'e', 'D', 'D', 'q', 'V', 'U', 'w', 'o', 'K', 'u', 'n', 'b', 'k', 'Y', 'M', 'L', 'H', 'L', 'X', 'H', 'r', 'D', 'o', 'A', 'Y', 'H'],41,),\n    (['0', '0', '0', '0', '1', '1', '1', '2', '2', '2', '2', '2', '2', '3', '3', '3', '3', '4', '4', '4', '4', '5', '5', '6', '6', '6', '7', '7', '7', '7', '7', '7', '8', '8', '9', '9', '9', '9'],['0', '0', '0', '0', '0', '1', '1', '1', '2', '2', '2', '3', '3', '4', '4', '4', '5', '5', '5', '5', '6', '6', '7', '7', '7', '7', '7', '8', '8', '8', '8', '9', '9', '9', '9', '9', '9', '9'],33,),\n    (['1', '0', '0', '1', '0', '1', '1', '1', '0', '0', '0', '1', '0', '0', '0', '1', '1', '0', '0', '0', '0', '1', '1'],['1', '1', '0', '0', '0', '1', '0', '1', '1', '0', '0', '0', '1', '0', '1', '0', '1', '1', '0', '1', '1', '0', '1'],13,),\n    ([' ', 'B', 'D', 'D', 'D', 'E', 'E', 'E', 'G', 'H', 'J', 'K', 'K', 'K', 'L', 'N', 'O', 'S', 'V', 'W', 'Y', 'Z', 'b', 'c', 'd', 'd', 'f', 'f', 'f', 'f', 'f', 'f', 'i', 'k', 'k', 'o', 't', 'u', 'v', 'x', 'x', 'z'],['G', 'G', 'J', 'K', 'L', 'N', 'Q', 'R', 'R', 'S', 'U', 'W', 'X', 'Y', 'Y', 'a', 'b', 'b', 'b', 'c', 'd', 'e', 'e', 'f', 'f', 'h', 'j', 'j', 'k', 'k', 'l', 'm', 'm', 'n', 'o', 's', 't', 't', 'w', 'z', 'z', 'z'],40,),\n    (['4'],['8'],0,),\n    (['0', '0', '0', '0', '0', '0', '0', '0', '0', '1', '1', '1', '1', '1', '1', '1', '1'],['0', '0', '0', '0', '0', '0', '0', '0', '1', '1', '1', '1', '1', '1', '1', '1', '1'],12,),\n    (['D', 'I', 'u', 'K', 'e', 's', 'n', 'z', 'd', 'y', 'S', 'P', 'y', 'r'],['N', 'h', 'M', 'N', 'n', 'F', 'Y', 'L', 'G', 'w', 'o', 'G', 'y', 'q'],7,)\n        ]\n    n_success = 0\n    for i, parameters_set in enumerate(param):\n        if f_filled(*parameters_set) == f_gold(*parameters_set):\n            n_success+=1\n    print(\"#Results: %i, %i\" % (n_success, len(param)))", "ref": "def myCopy ( s1 , s2 , index ) :\n    s2 [ index ] = s1 [ index ] ;\n    if ( index == len ( s1 ) - 1 ) :\n        return ;\n    myCopy ( s1 , s2 , index + 1 ) ;\n"}
Disassembly of <code object myCopy at 0x7f2b0163dc90, file "<dis>", line 1>:
2 0 LOAD_FAST 0 ( s1 )
2 LOAD_FAST 1 ( s2 )
4 BINARY_SUBSCR
6 LOAD_CONST 1 ( 1 )
8 BINARY_SUBSCR
10 LOAD_CONST 2 ( 0 )
12 COMPARE_OP 2 ( == )
14 POP_JUMP_IF_FALSE 20

3 16 LOAD_FAST 1 ( s2 )
18 LOAD_CONST 3 ( 1 )
20 BINARY_SUBSCR
22 LOAD_CONST 2 ( 0 )
24 COMPARE_OP 2 ( == )
26 POP_JUMP_IF_FALSE 36

4 28 LOAD_CONST 4 ( 0 )
30 RETURN_VALUE

5 >> 32 LOAD_GLOBAL 0 ( myCopy )
34 LOAD_FAST 1 ( s2 )
36 LOAD_FAST 1 ( s2 )
38 BINARY_SUBSCR
40 LOAD_CONST 2 ( 0 )
42 BINARY_SUBSCR
44 LOAD_CONST 2 ( 0 )
46 BINARY_SUBSCR
48 LOAD_CONST 2 ( 0 )
50 COMPARE_OP 2 ( == )
52 POP_JUMP_IF_FALSE 64

6 54 LOAD_CONST 4 ( 0 )
56 RETURN_VALUE

7 >> 58 LOAD_GLOBAL 1 ( print )
60 LOAD_FAST 1 ( s2 )
62 CALL_FUNCTION 1
64 POP_TOP

8 66 LOAD_CONST 5 ( '' )
68 RETURN_VALUE

10 >> 70 LOAD_GLOBAL 2 ( time )
72 LOAD_METHOD 3 ( sleep )
74 LOAD_CONST 6 ( 1 )
76 CALL_METHOD 1
78 POP_TOP

11 80 LOAD_CONST 7 ( 0 )
82 RETURN_VALUE
