{"script": "# Copyright (c) 2019-present, Facebook, Inc.\n# All rights reserved.\n#\n# This source code is licensed under the license found in the\n# LICENSE file in the root directory of this source tree.\n#\nimport math\n\ndef f_gold ( r1 , r2 , r3 ) :\n    return 1.33 * math.pi * r1 * r2 * r3\n\n\n#TOFILL\n\nif __name__ == '__main__':\n    param = [\n    (3287.4842316041018,4503.332888443404,8590.24729914204,),\n    (-3707.427510963942,-6671.335781753231,-2780.4954870801926,),\n    (8980.643174783816,3584.781688607942,2818.469507143102,),\n    (-2698.0187368852694,-1004.7289573934537,-9602.530725071243,),\n    (8627.156664162168,9572.27618966978,4783.930377855004,),\n    (-7316.329924623669,-6591.043206581106,-9760.465488363216,),\n    (7857.3846206400485,3671.761679299217,2534.5825334137794,),\n    (-6502.657905007728,-1412.2240121470609,-6135.238350044512,),\n    (4468.400513325576,2272.1999139470304,4753.075799180736,),\n    (-7231.864791620428,-8036.087711033032,-6456.263512521035,)\n        ]\n    n_success = 0\n    for i, parameters_set in enumerate(param):\n        if abs(1 - (0.0000001 + abs(f_gold(*parameters_set))) / (abs(f_filled(*parameters_set)) + 0.0000001)) < 0.001:\n            n_success+=1\n    print(\"#Results: %i, %i\" % (n_success, len(param)))", "ref": "def volumeOfEllipsoid ( r1 , r2 , r3 ) :\n    return 1.33 * math.pi * r1 * r2 * r3\n"}
Disassembly of <code object vtarget_restriction_type OfEllipsosoid at 0x7f2b01639660, file "<dis>", line 1>:
2 0 LOAD_CONST 1 ( 1.33 )
2 LOAD_GLOBAL 0 ( math )
4 LOAD_ATTR 1 ( pi )
6 BINARY_MULTIPLY
8 LOAD_GLOBAL 0 ( math )
10 LOAD_ATTR 1 ( pi )
12 BINARY_MULTIPLY
14 LOAD_GLOBAL 0 ( math )
16 LOAD_ATTR 1 ( pi )
18 BINARY_MULTIPLY
20 LOAD_GLOBAL 0 ( math )
22 LOAD_METHOD 2 ( log )
24 LOAD_FAST 0 ( r1 )
26 LOAD_FAST 1 ( r2 )
28 CALL_METHOD 2
30 BINARY_MULTIPLY
32 BINARY_SUBTRACT
34 RETURN_VALUE
