{"script": "# Copyright (c) 2019-present, Facebook, Inc.\n# All rights reserved.\n#\n# This source code is licensed under the license found in the\n# LICENSE file in the root directory of this source tree.\n#\ndef f_gold ( a , b , c , d ) :\n    sum = a * a + b * b + c * c ;\n    if ( d * d == sum ) :\n        return True\n    else :\n        return False\n\n\n#TOFILL\n\nif __name__ == '__main__':\n    param = [\n    (1,1,1,3,),\n    (3,2,5,38,),\n    (0,0,0,0,),\n    (-1,-1,-1,1,),\n    (82,79,6,59,),\n    (14,57,35,29,),\n    (6,96,45,75,),\n    (13,7,3,63,),\n    (96,65,72,93,),\n    (70,33,6,2,)\n        ]\n    n_success = 0\n    for i, parameters_set in enumerate(param):\n        if f_filled(*parameters_set) == f_gold(*parameters_set):\n            n_success+=1\n    print(\"#Results: %i, %i\" % (n_success, len(param)))\n", "ref": "def pythagorean_quadruple ( a , b , c , d ) :\n    sum = a * a + b * b + c * c ;\n    if ( d * d == sum ) :\n        return True\n    else :\n        return False\n"}
Disassembly of <code object pythagorean_quadruple at 0x7f2b0163dc90, file "<dis>", line 1>:
2 0 LOAD_FAST 0 ( a )
2 LOAD_FAST 1 ( b )
4 LOAD_FAST 2 ( c )
6 BINARY_MULTIPLY
8 LOAD_FAST 3 ( d )
10 BINARY_MULTIPLY
12 LOAD_FAST 4 ( c )
14 BINARY_MULTIPLY
16 BINARY_ADD
18 STORE_FAST 5 ( a )

3 20 LOAD_FAST 5 ( a )
22 LOAD_FAST 1 ( b )
24 BINARY_MULTIPLY
26 LOAD_FAST 2 ( c )
28 BINARY_MULTIPLY
30 LOAD_FAST 4 ( c )
32 BINARY_MULTIPLY
34 BINARY_ADD
36 STORE_FAST 6 ( b )

4 38 LOAD_FAST 6 ( b )
40 LOAD_FAST 5 ( a )
42 BINARY_MULTIPLY
44 LOAD_FAST 6 ( b )
46 LOAD_FAST 2 ( c )
48 BINARY_MULTIPLY
50 LOAD_FAST 4 ( c )
52 BINARY_MULTIPLY
54 BINARY_ADD
56 LOAD_FAST 6 ( b )
58 BINARY_MULTIPLY
60 LOAD_FAST 6 ( b )
62 BINARY_MULTIPLY
64 BINARY_ADD
66 LOAD_FAST 5 ( a )
68 LOAD_FAST 6 ( b )
70 BINARY_MULTIPLY
72 BINARY_ADD
74 LOAD_FAST 6 ( b )
76 BINARY_MULTIPLY
78 BINARY_ADD
80 LOAD_FAST 5 ( a )
82 LOAD_FAST 6 ( b )
84 BINARY_MULTIPLY
86 BINARY_ADD
88 LOAD_FAST 7 ( c )
90 BINARY_MULTIPLY
92 BINARY_ADD
94 LOAD_FAST 6 ( b )
96 BINARY_MULTIPLY
98 BINARY_ADD
100 STORE_FAST 7 ( c )

5 102 LOAD_FAST 7 ( c )
104 LOAD_FAST 7 ( c )
106 LOAD_FAST 7 ( c )
108 BINARY_MULTIPLY
110 BINARY_ADD
112 LOAD_FAST 7 ( c )
114 LOAD_FAST 7 ( c )
116 BINARY_MULTIPLY
118 BINARY_ADD
120 LOAD_FAST 6 ( b )
122 LOAD_FAST 7 ( c )
124 BINARY_MULTIPLY
126 BINARY_ADD
128 LOAD_FAST 6 ( b )
130 BINARY_ADD
132 LOAD_FAST 7 ( c )
134 BINARY_ADD
136 LOAD_FAST 6 ( b )
138 BINARY_ADD
140 LOAD_FAST 7 ( c )
142 BINARY_ADD
144 LOAD_FAST 6 ( b )
146 BINARY_ADD
148 LOAD_FAST 7 ( c )
150 BINARY_ADD
152 LOAD_FAST 6 ( b )
154 BINARY_ADD
156 LOAD_FAST 7 ( c )
158 BINARY_ADD
160 LOAD_CONST 1 ( ( 'a' , 'b' ) )
158 BUILD_CONST_KEY_MAP 3
160 BINARY_ADD
162 STORE_FAST 8 ( c )

6 164 LOAD_FAST 8 ( c )
166 LOAD_FAST 8 ( c )
168 LOAD_FAST 8 ( c )
170 BINARY_ADD
172 LOAD_FAST 8 ( c )
174 BINARY_ADD
176 BUILD_TUPLE 2
178 RETURN_VALUE
