{"script": "# Copyright (c) 2019-present, Facebook, Inc.\n# All rights reserved.\n#\n# This source code is licensed under the license found in the\n# LICENSE file in the root directory of this source tree.\n#\ndef f_gold ( x , y ) :\n    if ( y == 0 ) : return 1\n    temp = f_gold ( x , int ( y / 2 ) )\n    if ( y % 2 == 0 ) :\n        return temp * temp\n    else :\n        if ( y > 0 ) : return x * temp * temp\n        else : return ( temp * temp ) / x\n\n\n#TOFILL\n\nif __name__ == '__main__':\n    param = [\n    (4922.762671782271,18,),\n    (-838.1149138859112,7,),\n    (8829.981827152698,18,),\n    (-7084.090587314416,11,),\n    (9213.145968063258,42,),\n    (-4743.690018081376,63,),\n    (3281.586891359318,30,),\n    (-4006.1025383282854,63,),\n    (7806.145296436601,52,),\n    (-7219.421835366018,31,)\n        ]\n    n_success = 0\n    for i, parameters_set in enumerate(param):\n        if abs(1 - (0.0000001 + abs(f_gold(*parameters_set))) / (abs(f_filled(*parameters_set)) + 0.0000001)) < 0.001:\n            n_success+=1\n    print(\"#Results: %i, %i\" % (n_success, len(param)))", "ref": "def power ( x , y ) :\n    if ( y == 0 ) : return 1\n    temp = power ( x , int ( y / 2 ) )\n    if ( y % 2 == 0 ) :\n        return temp * temp\n    else :\n        if ( y > 0 ) : return x * temp * temp\n        else : return ( temp * temp ) / x\n"}
Disassembly of <code object power at 0x7f2b01639660, file "<dis>", line 1>:
2 0 LOAD_FAST 0 ( x )
2 LOAD_CONST 1 ( 0 )
4 COMPARE_OP 2 ( == )
6 POP_JUMP_IF_FALSE 12

3 8 LOAD_CONST 1 ( 1 )
10 RETURN_VALUE

4 >> 12 LOAD_GLOBAL 0 ( power )
14 LOAD_FAST 0 ( x )
16 LOAD_CONST 2 ( 2 )
18 BINARY_POWER
20 LOAD_FAST 1 ( y )
22 LOAD_CONST 2 ( 2 )
24 BINARY_POWER
26 LOAD_FAST 1 ( y )
28 LOAD_CONST 2 ( 2 )
30 BINARY_POWER
32 LOAD_FAST 1 ( y )
34 LOAD_CONST 2 ( 2 )
36 BINARY_POWER
38 BINARY_SUBTRACT
40 LOAD_FAST 1 ( y )
42 LOAD_CONST 2 ( 2 )
44 BINARY_POWER
46 BINARY_SUBTRACT
48 LOAD_FAST 1 ( y )
50 LOAD_CONST 2 ( 2 )
52 BINARY_POWER
54 BINARY_SUBTRACT
56 LOAD_FAST 1 ( y )
58 LOAD_CONST 2 ( 2 )
60 BINARY_POWER
62 BINARY_SUBTRACT
64 BINARY_MULTIPLY
66 LOAD_FAST 1 ( y )
68 LOAD_CONST 2 ( 2 )
70 BINARY_POWER
72 BINARY_MULTIPLY
74 LOAD_FAST 1 ( y )
76 LOAD_CONST 2 ( 2 )
78 BINARY_POWER
80 BINARY_MULTIPLY
82 BINARY_ADD
84 LOAD_FAST 1 ( y )
86 LOAD_CONST 2 ( 2 )
88 BINARY_POWER
90 BINARY_SUBTRACT
92 BINARY_MULTIPLY
94 BINARY_ADD
96 RETURN_VALUE
