{"script": "# Copyright (c) 2019-present, Facebook, Inc.\n# All rights reserved.\n#\n# This source code is licensed under the license found in the\n# LICENSE file in the root directory of this source tree.\n#\ndef f_gold ( a , n , k ) :\n    if k >= n - 1 :\n        return n\n    best = 0\n    times = 0\n    for i in range ( n ) :\n        if a [ i ] > best :\n            best = a [ i ]\n            if i == True :\n                times = 1\n        else :\n            times += 1\n        if times >= k :\n            return best\n    return best\n\n\n#TOFILL\n\nif __name__ == '__main__':\n    param = [\n    ([2, 5, 5, 9, 10, 10, 11, 14, 23, 27, 31, 32, 33, 33, 33, 37, 39, 41, 41, 42, 42, 43, 47, 60, 61, 68, 73, 73, 73, 78, 80, 80, 82, 83, 86, 87, 89, 92, 94, 98],33,37,),\n    ([80, -58, 64, 48, -16, 60, -50, -52, 62, -86, -96, 52, 26, -30, 14],14,13,),\n    ([0, 0, 0, 0, 0, 0, 0, 0, 0, 1, 1],7,6,),\n    ([90, 23, 43, 42, 7, 71, 79],4,4,),\n    ([-96, -96, -90, -84, -68, -64, -56, -56, -50, -50, -48, -46, -28, -18, 0, 0, 6, 32, 32, 34, 42, 42, 46, 50, 50, 52, 64, 64, 70, 76, 84, 88],28,21,),\n    ([1, 1, 1],1,2,),\n    ([2, 9, 15, 19, 26, 29, 42, 45, 46, 47, 55, 60, 60, 61, 62, 64, 68, 69, 74, 79, 96],14,17,),\n    ([-32, 12, 80, 42, 80, 8, 58, -76, -42, -98, 22, -90, -16, -4, -62, -32, 28, 12, 78, -52, -84, 78, 88, -76, -52, 68, -34, -16, -4, 2, -78, -94, -22, 34, 6, -62, 72],26,31,),\n    ([0, 0, 0, 0, 0, 0, 0, 0, 0, 0, 0, 1, 1, 1, 1, 1, 1, 1, 1, 1, 1, 1, 1, 1, 1, 1, 1],26,14,),\n    ([52, 19],1,1,)\n        ]\n    n_success = 0\n    for i, parameters_set in enumerate(param):\n        if f_filled(*parameters_set) == f_gold(*parameters_set):\n            n_success+=1\n    print(\"#Results: %i, %i\" % (n_success, len(param)))", "ref": "def winner ( a , n , k ) :\n    if k >= n - 1 :\n        return n\n    best = 0\n    times = 0\n    for i in range ( n ) :\n        if a [ i ] > best :\n            best = a [ i ]\n            if i == True :\n                times = 1\n        else :\n            times += 1\n        if times >= k :\n            return best\n    return best\n"}
Disassembly of <code object winner at 0x7f816a6e4b70, file "<dis>", line 19>:
20 0 LOAD_FAST 0 ( a )
2 LOAD_CONST 1 ( 1 )
4 BINARY_SUBSCR
6 STORE_FAST 1 ( n )

21 8 LOAD_FAST 1 ( n )
10 LOAD_CONST 2 ( 0 )
12 BINARY_SUBSCR
14 STORE_FAST 2 ( n )

22 16 LOAD_FAST 2 ( n )
18 LOAD_CONST 3 ( 1 )
20 BINARY_SUBSCR
22 STORE_FAST 3 ( n )

23 24 LOAD_FAST 1 ( n )
26 LOAD_CONST 4 ( 2 )
28 BINARY_SUBSCR
30 STORE_FAST 4 ( n )

24 32 LOAD_FAST 0 ( a )
34 LOAD_FAST 4 ( n )
36 LOAD_CONST 5 ( 1 )
38 BINARY_SUBSCR
40 LOAD_FAST 2 ( n )
42 LOAD_CONST 6 ( 2 )
44 BINARY_SUBSCR
46 LOAD_FAST 3 ( n )
48 LOAD_CONST 7 ( 3 )
50 BINARY_SUBSCR
52 LOAD_FAST 4 ( n )
54 LOAD_CONST 8 ( 2 )
56 BINARY_SUBSCR
58 LOAD_CONST 9 ( 3 )
60 BINARY_SUBSCR
62 LOAD_FAST 4 ( n )
64 LOAD_CONST 10 ( 2 )
66 BINARY_SUBSCR
68 LOAD_FAST 4 ( n )
70 LOAD_CONST 11 ( 3 )
72 BINARY_SUBSCR
74 LOAD_CONST 12 ( ( 'n' , 'n' , 'n' , 'n' , 'n' , 'n' , 'n' , 'n' , 'n' , 'n' , 'n' , 'n' , 'n' , 'n' , 'n' , 'n' , 'n' , 'n' , 'n' , 'n' , 'n' , 'n' , 'n' , 'n' , 'n' , 'n' , 'n' , 'n' , 'n' , 'n' , 'n' , 'n' , 'n' , 'n' , 'n' , 'n' , 'n' , 'n' , 'n' , 'n' , 'n' , 'n' , 'n' , 'n' , 'n' , 'n' , 'n' , 'n' , 'n' , 'n' , 'n' , 'n' , 'n' , 'n' , 'n' , 'n' , 'n' , 'n' ) )
10 BUILD_CONST_KEY_MAP 5
12 RETURN_VALUE

