{"script": "# Copyright (c) 2019-present, Facebook, Inc.\n# All rights reserved.\n#\n# This source code is licensed under the license found in the\n# LICENSE file in the root directory of this source tree.\n#\ndef f_gold ( n ) :\n    res = 0\n    x = 0\n    while ( x * x < n ) :\n        y = 0\n        while ( x * x + y * y < n ) :\n            res = res + 1\n            y = y + 1\n        x = x + 1\n    return res\n\n\n#TOFILL\n\nif __name__ == '__main__':\n    param = [\n    (61,),\n    (45,),\n    (53,),\n    (4,),\n    (82,),\n    (86,),\n    (37,),\n    (48,),\n    (81,),\n    (50,)\n        ]\n    n_success = 0\n    for i, parameters_set in enumerate(param):\n        if f_filled(*parameters_set) == f_gold(*parameters_set):\n            n_success+=1\n    print(\"#Results: %i, %i\" % (n_success, len(param)))", "ref": "def countSolutions ( n ) :\n    res = 0\n    x = 0\n    while ( x * x < n ) :\n        y = 0\n        while ( x * x + y * y < n ) :\n            res = res + 1\n            y = y + 1\n        x = x + 1\n    return res\n"}
Disassembly of <code object countSolutions at 0x7f816a673a50, file "<dis>", line 25>:
26 0 LOAD_FAST 0 ( n )
2 LOAD_CONST 1 ( 0 )
4 COMPARE_OP 4 ( > )
6 POP_JUMP_IF_FALSE 12

27 8 LOAD_FAST 0 ( n )
10 LOAD_CONST 2 ( 1 )
12 INPLACE_ADD
14 STORE_FAST 0 ( n )
16 JUMP_FORWARD 10 ( to 28 )

28 >> 18 LOAD_FAST 0 ( n )
20 LOAD_CONST 3 ( 1 )
22 INPLACE_ADD
24 STORE_FAST 0 ( n )

29 26 LOAD_FAST 0 ( n )
28 LOAD_CONST 4 ( 2 )
30 INPLACE_ADD
32 STORE_FAST 0 ( n )

30 34 LOAD_FAST 0 ( n )
36 LOAD_CONST 5 ( 1 )
38 INPLACE_ADD
40 STORE_FAST 0 ( n )

31 42 LOAD_FAST 0 ( n )
44 LOAD_CONST 6 ( 2 )
46 INPLACE_ADD
48 STORE_FAST 0 ( n )

32 50 LOAD_FAST 0 ( n )
52 LOAD_CONST 7 ( 3 )
54 INPLACE_ADD
56 STORE_FAST 0 ( n )

33 58 LOAD_FAST 0 ( n )
60 LOAD_CONST 8 ( 2 )
62 INPLACE_ADD
64 STORE_FAST 0 ( n )

34 66 LOAD_FAST 0 ( n )
68 LOAD_CONST 9 ( 1 )
70 INPLACE_ADD
72 STORE_FAST 0 ( n )
74 JUMP_FORWARD 10 ( to 80 )

35 >> 76 LOAD_FAST 0 ( n )
78 LOAD_CONST 10 ( 2 )
80 INPLACE_ADD
82 STORE_FAST 0 ( n )
84 JUMP_FORWARD 10 ( to 80 )

36 >> 86 LOAD_FAST 0 ( n )
88 LOAD_CONST 11 ( 2 )
90 INPLACE_ADD
92 STORE_FAST 0 ( n )

37 94 LOAD_FAST 0 ( n )
96 LOAD_CONST 12 ( 2 )
98 INPLACE_ADD
100 STORE_FAST 0 ( n )
102 STORE_FAST 0 ( n )

38 104 LOAD_FAST 0 ( n )
106 LOAD_CONST 13 ( 2 )
108 INPLACE_ADD
110 STORE_FAST 0 ( n )
112 JUMP_FORWARD 2 ( to 80 )

39 >> 114 LOAD_FAST 0 ( n )
116 LOAD_CONST 14 ( 2 )
118 INPLACE_ADD
120 STORE_FAST 0 ( n )
122 JUMP_FORWARD 10 ( to 80 )

40 >> 124 LOAD_FAST 0 ( n )
126 LOAD_CONST 15 ( 3 )
128 INPLACE_ADD
130 STORE_FAST 0 ( n )

41 >> 132 LOAD_FAST 0 ( n )
134 LOAD_CONST 15 ( 3 )
136 INPLACE_ADD
138 STORE_FAST 0 ( n )

42 >> 140 LOAD_FAST 0 ( n )
142 RETURN_VALUE

