{"script": "# Copyright (c) 2019-present, Facebook, Inc.\n# All rights reserved.\n#\n# This source code is licensed under the license found in the\n# LICENSE file in the root directory of this source tree.\n#\ndef f_gold ( arr , n ) :\n    arr.sort ( )\n    max_count = 1 ; res = arr [ 0 ] ; curr_count = 1\n    for i in range ( 1 , n ) :\n        if ( arr [ i ] == arr [ i - 1 ] ) :\n            curr_count += 1\n        else :\n            if ( curr_count > max_count ) :\n                max_count = curr_count\n                res = arr [ i - 1 ]\n            curr_count = 1\n    if ( curr_count > max_count ) :\n        max_count = curr_count\n        res = arr [ n - 1 ]\n    return res\n\n\n#TOFILL\n\nif __name__ == '__main__':\n    param = [\n    ([1, 1, 3, 11, 11, 11, 18, 20, 26, 26, 27, 30, 33, 39, 39, 42, 42, 48, 51, 51, 51, 51, 60, 66, 66, 68, 68, 69, 71, 72, 73, 76, 76, 77, 77, 77, 78, 90, 96],25,),\n    ([46, -8, 64, -46, -38, 92, -14, -22, -32, 48, 72, 96, 30, 66, 94, 36, 42, -18, 14, -74, 80, 96, -4],18,),\n    ([0, 0, 0, 0, 0, 0, 1],6,),\n    ([93, 32, 3, 31, 67, 96, 52, 80, 70, 49, 45, 23, 58, 87, 31, 56, 21, 71, 55, 97],15,),\n    ([-98, -96, -84, -82, -72, -64, -62, -56, -52, -52, -48, -46, -42, -36, -32, -30, -30, -18, -16, -10, -2, 0, 6, 18, 22, 22, 40, 42, 50, 54, 64, 68, 68, 72, 80, 82, 84, 96],20,),\n    ([1, 1, 0, 0, 0, 1, 0, 0, 0, 1, 0, 0, 0, 1, 1, 1, 1, 0, 0, 1, 0, 0, 1, 0, 0, 1, 0, 1, 0, 0, 0, 1, 1, 1, 0, 0, 1, 0, 1, 1, 0],29,),\n    ([9, 12, 13, 28, 43, 46, 64, 66, 68, 89, 92],6,),\n    ([22, -8, -56, 68, -12, -26, -40, -46, -42, -80, 4, -42, -72, -22, 36, 22, -94, 48, 96, 80, -52, 46, 90, 94, 36, 92, -12, -24, -60, -32, 92, 18, 76, 40, -32, 6, -22, 86, 86, -88, 38, 50, 32, 78, -82, 54, -40, 18],41,),\n    ([0, 0, 0, 0, 0, 0, 1, 1, 1],4,),\n    ([81, 74, 32, 41, 85, 65, 81, 74, 40, 64, 97, 4, 61, 43, 54, 96, 62, 2, 97, 86, 80, 25, 9, 31, 16, 29, 4, 63, 76, 41, 5, 95],16,)\n        ]\n    n_success = 0\n    for i, parameters_set in enumerate(param):\n        if f_filled(*parameters_set) == f_gold(*parameters_set):\n            n_success+=1\n    print(\"#Results: %i, %i\" % (n_success, len(param)))", "ref": "def mostFrequent ( arr , n ) :\n    arr.sort ( )\n    max_count = 1 ; res = arr [ 0 ] ; curr_count = 1\n    for i in range ( 1 , n ) :\n        if ( arr [ i ] == arr [ i - 1 ] ) :\n            curr_count += 1\n        else :\n            if ( curr_count > max_count ) :\n                max_count = curr_count\n                res = arr [ i - 1 ]\n            curr_count = 1\n    if ( curr_count > max_count ) :\n        max_count = curr_count\n        res = arr [ n - 1 ]\n    return res\n"}
Disassembly of <code object mostFrequent at 0x7f816a673a50, file "<dis>", line 89>:
90 0 LOAD_FAST 0 ( arr )
2 LOAD_METHOD 0 ( sort )
4 CALL_METHOD 0
6 STORE_FAST 1 ( n )

92 8 LOAD_FAST 1 ( n )
10 LOAD_CONST 1 ( 1 )
12 INPLACE_ADD
14 STORE_FAST 1 ( n )

93 16 LOAD_FAST 1 ( n )
18 LOAD_CONST 2 ( 1 )
20 INPLACE_ADD
22 STORE_FAST 1 ( n )

94 24 LOAD_FAST 1 ( n )
26 LOAD_CONST 3 ( 1 )
28 INPLACE_ADD
30 STORE_FAST 1 ( n )

95 32 LOAD_FAST 1 ( n )
34 LOAD_CONST 4 ( 2 )
36 INPLACE_ADD
38 STORE_FAST 1 ( n )

96 40 LOAD_FAST 1 ( n )
42 LOAD_CONST 5 ( 1 )
44 INPLACE_ADD
46 STORE_FAST 1 ( n )

97 48 LOAD_FAST 1 ( n )
50 LOAD_CONST 6 ( 2 )
52 INPLACE_ADD
54 STORE_FAST 1 ( n )

98 56 LOAD_FAST 1 ( n )
58 LOAD_CONST 7 ( 3 )
60 INPLACE_ADD
62 STORE_FAST 1 ( n )

99 64 LOAD_FAST 1 ( n )
66 LOAD_CONST 8 ( 2 )
68 INPLACE_ADD
70 STORE_FAST 1 ( n )

100 72 LOAD_FAST 1 ( n )
74 LOAD_CONST 9 ( 4 )
76 INPLACE_ADD
78 STORE_FAST 1 ( n )

101 80 LOAD_FAST 1 ( n )
82 LOAD_CONST 10 ( 4 )
84 INPLACE_ADD
86 STORE_FAST 1 ( n )

102 88 LOAD_FAST 1 ( n )
90 LOAD_CONST 11 ( 2 )
92 INPLACE_ADD
94 STORE_FAST 1 ( n )

103 96 LOAD_FAST 1 ( n )
98 LOAD_CONST 12 ( 2 )
100 INPLACE_ADD
102 STORE_FAST 1 ( n )

104 104 LOAD_FAST 1 ( n )
106 LOAD_CONST 13 ( 2 )
108 INPLACE_ADD
110 STORE_FAST 1 ( n )

105 112 LOAD_FAST 1 ( n )
114 LOAD_FAST 1 ( n )
116 LOAD_CONST 14 ( 2 )
118 INPLACE_ADD
120 INPLACE_ADD
122 STORE_FAST 1 ( n )

106 124 LOAD_FAST 1 ( n )
126 LOAD_CONST 15 ( 3 )
128 INPLACE_ADD
130 STORE_FAST 1 ( n )

107 132 LOAD_FAST 1 ( n )
134 LOAD_FAST 1 ( n )
136 INPLACE_ADD
138 STORE_FAST 1 ( n )

108 140 LOAD_FAST 1 ( n )
142 LOAD_FAST 1 ( n )
144 LOAD_CONST 15 ( 2 )
146 INPLACE_ADD
148 STORE_FAST 1 ( n )

109 150 LOAD_FAST 1 ( n )
152 RETURN_VALUE