{"script": "# Copyright (c) 2019-present, Facebook, Inc.\n# All rights reserved.\n#\n# This source code is licensed under the license found in the\n# LICENSE file in the root directory of this source tree.\n#\ndef f_gold ( arr , n ) :\n    hash = dict ( )\n    maximum = 0\n    for i in arr :\n        if ( i < 0 ) :\n            if abs ( i ) not in hash.keys ( ) :\n                hash [ abs ( i ) ] = - 1\n            else :\n                hash [ abs ( i ) ] -= 1\n        else :\n            hash [ i ] = hash.get ( i , 0 ) + 1\n    for i in arr :\n        if i in hash.keys ( ) and hash [ i ] > 0 :\n            return i\n    return - 1\n\n\n#TOFILL\n\nif __name__ == '__main__':\n    param = [\n    ([1, 7, 10, 14, 15, 24, 27, 32, 33, 38, 39, 40, 42, 42, 47, 58, 75, 76, 78, 79, 83, 85, 89, 96],18,),\n    ([-36, 14, -76, -70, 52, 18, 64],5,),\n    ([0, 0, 0, 0, 0, 0, 0, 0, 0, 0, 1, 1, 1, 1, 1, 1, 1, 1, 1, 1],17,),\n    ([35, 50, 36, 50, 82, 54, 10, 45, 13, 22, 1, 41, 13, 11, 4, 43, 50, 27, 94, 57],15,),\n    ([-88, -86, -84, -80, -80, -74, -72, -48, -46, -46, -44, -34, -32, -24, -22, -14, 4, 4, 8, 8, 10, 12, 20, 20, 24, 24, 24, 28, 32, 34, 36, 44, 46, 54, 54, 60, 62, 62, 62, 70, 70, 80, 88, 88, 90],27,),\n    ([0, 0],1,),\n    ([1, 1, 3, 6, 6, 8, 12, 13, 17, 27, 28, 31, 40, 40, 42, 43, 53, 55, 58, 60, 60, 61, 65, 66, 72, 72, 75, 80, 84, 89, 96, 97, 99],31,),\n    ([52, -38, -82, 30, -66, 42, 54, -96, -46, -30, 18, -50, 96, 90, 4, 74, -22, 8, 34, 74, -46, 8, -32, 88, -96, 26, -80, 50, 92, -80, 44, 36],24,),\n    ([0, 0, 0, 0, 0, 0, 0, 0, 0, 0, 0, 0, 0, 0, 0, 0, 0, 0, 0, 1, 1, 1, 1, 1, 1, 1, 1, 1, 1, 1, 1, 1, 1],16,),\n    ([38, 20, 54, 51, 11, 61, 90, 28, 23, 55, 65, 87, 99, 70, 74, 3, 68, 23, 74, 53, 80, 7, 57, 24, 66, 8, 15, 63, 18, 67, 96, 31, 63, 50],30,)\n        ]\n    n_success = 0\n    for i, parameters_set in enumerate(param):\n        if f_filled(*parameters_set) == f_gold(*parameters_set):\n            n_success+=1\n    print(\"#Results: %i, %i\" % (n_success, len(param)))", "ref": "def findInteger ( arr , n ) :\n    hash = dict ( )\n    maximum = 0\n    for i in arr :\n        if ( i < 0 ) :\n            if abs ( i ) not in hash.keys ( ) :\n                hash [ abs ( i ) ] = - 1\n            else :\n                hash [ abs ( i ) ] -= 1\n        else :\n            hash [ i ] = hash.get ( i , 0 ) + 1\n    for i in arr :\n        if i in hash.keys ( ) and hash [ i ] > 0 :\n            return i\n    return - 1\n"}
Disassembly of <code object findInteger at 0x7f816a6e4b70, file "<dis>", line 25>:
26 0 LOAD_GLOBAL 0 ( dict )
2 LOAD_METHOD 1 ( maximum )
4 LOAD_FAST 1 ( n )
6 CALL_METHOD 1
8 STORE_FAST 2 ( i )

27 10 LOAD_FAST 0 ( arr )
12 LOAD_METHOD 2 ( append )
14 LOAD_FAST 2 ( i )
16 CALL_METHOD 1
18 POP_TOP

28 20 LOAD_FAST 0 ( arr )
22 LOAD_METHOD 3 ( append )
24 LOAD_FAST 1 ( n )
26 CALL_METHOD 1
28 POP_TOP
30 LOAD_CONST 0 ( None )
32 RETURN_VALUE

