{"script": "# Copyright (c) 2019-present, Facebook, Inc.\n# All rights reserved.\n#\n# This source code is licensed under the license found in the\n# LICENSE file in the root directory of this source tree.\n#\ndef f_gold ( a , b , n , k ) :\n    a.sort ( reverse = True )\n    b.sort ( )\n    for i in range ( n ) :\n        if ( a [ i ] + b [ i ] < k ) :\n            return False\n    return True\n\n\n#TOFILL\n\nif __name__ == '__main__':\n    param = [\n    ([9, 12, 16, 25, 27, 40, 43, 52, 52, 70, 87, 88, 90, 97, 99],[4, 7, 11, 20, 34, 35, 36, 44, 46, 71, 72, 78, 85, 85, 91],10,7,),\n    ([-96, -90, -80, 10, -84, -96, -28, -42, 30, -92, -44, -14, 18, -68, -94, 6, -76, 72, -90, 42, 70, -78, 56, -26, 8, 74, 12, -74, 20, -86, -74, -90, -98, 92, 30, 94, 14, 92, 88, -98, 42, -48],[-48, 84, 16, -72, 96, -78, -76, -84, -76, -32, -50, 62, -22, 24, -32, 94, 8, -14, -20, 44, -80, 68, -44, 60, 94, -42, -44, -74, -98, -86, 16, 62, -80, 18, -18, 70, 30, 40, -56, 76, -32, 50],40,38,),\n    ([0, 0, 0, 0, 0, 0, 0, 1, 1, 1, 1, 1, 1, 1, 1, 1, 1, 1],[0, 0, 0, 0, 0, 0, 0, 0, 0, 0, 0, 0, 1, 1, 1, 1, 1, 1],11,15,),\n    ([13, 35, 6, 69, 42, 55, 11, 97, 15, 65, 70, 77, 51, 16, 3, 26, 47, 72, 15, 71, 2, 31, 18, 59, 75, 48],[88, 15, 44, 36, 38, 98, 89, 81, 73, 51, 37, 4, 79, 60, 11, 62, 48, 45, 12, 21, 65, 14, 78, 20, 12, 46],25,16,),\n    ([-72, -70, -66, -64, -52, -52, -52, -48, -46, -42, -40, -34, -20, -4, -4, -2, 2, 4, 16, 16, 18, 18, 32, 36, 52, 54, 56, 56, 58, 68, 72, 74, 84, 84, 90, 90, 92, 94],[-94, -76, -74, -56, -54, -50, -46, -38, -26, -24, -24, -22, -16, -10, -6, -4, -4, 0, 0, 6, 12, 12, 18, 20, 38, 50, 52, 52, 54, 64, 64, 72, 72, 72, 76, 90, 96, 96],26,30,),\n    ([1, 0, 0, 1, 0, 1, 1, 0, 1, 0, 1, 1, 1, 0, 0, 1, 0, 1, 0],[1, 1, 0, 0, 0, 1, 0, 1, 0, 1, 1, 1, 1, 1, 0, 1, 0, 0, 1],13,13,),\n    ([8, 17, 18, 21, 23, 32, 34, 37, 44, 48, 53, 58, 64, 66, 66, 72, 72, 79, 80, 80, 80, 82, 87, 92, 93, 94, 96, 96, 98],[11, 15, 17, 19, 23, 23, 26, 27, 36, 43, 46, 47, 55, 59, 63, 66, 77, 79, 79, 82, 85, 86, 86, 91, 91, 94, 94, 97, 99],20,14,),\n    ([-20, -22, -16, -80, -88, 22, -78, -82, -50, 32, 28, -8, -48, 80, 62, -14, 14, 10, -78, 78, 52, 94, -66, 14, 50, 18, -38, -98, 24, 18, -28, 24, 10, -88, -14],[6, -54, 90, 98, -30, 88, 36, 88, 38, 12, 46, -66, -80, 32, 42, -96, 62, -44, -80, -14, 20, 2, 70, -46, 96, -40, 52, 56, 96, -82, 24, 98, -16, 90, 66],31,24,),\n    ([0, 0, 0, 0, 0, 0, 0, 0, 0, 0, 0, 0, 0, 0, 0, 0, 0, 0, 0, 0, 0, 0, 1, 1, 1, 1, 1, 1, 1, 1, 1, 1, 1, 1, 1, 1, 1, 1, 1, 1, 1, 1, 1, 1],[0, 0, 0, 0, 0, 0, 0, 0, 0, 0, 0, 0, 0, 0, 0, 0, 0, 0, 0, 0, 0, 0, 0, 0, 0, 0, 0, 0, 1, 1, 1, 1, 1, 1, 1, 1, 1, 1, 1, 1, 1, 1, 1, 1],31,30,),\n    ([75, 31, 58, 10, 92, 65, 45, 72, 53, 91, 39, 33, 10, 13, 67, 85],[41, 91, 78, 28, 40, 71, 74, 69, 71, 12, 7, 21, 92, 19, 39, 34],14,8,)\n        ]\n    n_success = 0\n    for i, parameters_set in enumerate(param):\n        if f_filled(*parameters_set) == f_gold(*parameters_set):\n            n_success+=1\n    print(\"#Results: %i, %i\" % (n_success, len(param)))", "ref": "def isPossible ( a , b , n , k ) :\n    a.sort ( reverse = True )\n    b.sort ( )\n    for i in range ( n ) :\n        if ( a [ i ] + b [ i ] < k ) :\n            return False\n    return True\n"}
Disassembly of <code object isPossible at 0x7f816a673a50, file "<dis>", line 202>:
204 0 LOAD_FAST 0 ( a )
2 LOAD_METHOD 0 ( sort )
4 CALL_METHOD 0
6 STORE_FAST 1 ( b )

205 8 LOAD_FAST 1 ( b )
10 LOAD_METHOD 1 ( sort )
12 CALL_METHOD 0
14 STORE_FAST 2 ( a )

206 16 LOAD_FAST 2 ( a )
18 LOAD_METHOD 2 ( sort )
20 CALL_METHOD 0
22 POP_TOP

207 24 LOAD_FAST 0 ( a )
26 LOAD_METHOD 3 ( sort )
28 CALL_METHOD 0
30 POP_TOP
32 LOAD_CONST 0 ( None )
34 RETURN_VALUE

