{"script": "# Copyright (c) 2019-present, Facebook, Inc.\n# All rights reserved.\n#\n# This source code is licensed under the license found in the\n# LICENSE file in the root directory of this source tree.\n#\ndef f_gold ( array , start , end ) :\n    if ( start > end ) :\n        return end + 1\n    if ( start != array [ start ] ) :\n        return start ;\n    mid = int ( ( start + end ) / 2 )\n    if ( array [ mid ] == mid ) :\n        return f_gold ( array , mid + 1 , end )\n    return f_gold ( array , start , mid )\n\n\n#TOFILL\n\nif __name__ == '__main__':\n    param = [\n    ([3, 6, 7, 9, 11, 14, 18, 30, 30, 32, 32, 34, 37, 44, 45, 45, 48, 48, 48, 52, 58, 60, 63, 67, 69, 69, 81, 83, 87, 89, 97, 99],24,18,),\n    ([88, -62, 16, 80, 66, 78, 88, 38, 52, -96, 48, 98, 96, -62, 18, 34, -58, 30, -10, 26, -98, 48, -96, 4, 92, 36, 36, -36, -32, -70, 62, -58, -58, -84, 86, -98],19,26,),\n    ([0, 0, 0, 0, 0, 0, 0, 0, 0, 0, 0, 0, 0, 0, 0, 0, 0, 0, 0, 0, 1, 1, 1, 1, 1, 1, 1, 1, 1, 1, 1, 1, 1, 1, 1, 1, 1, 1, 1, 1, 1, 1],26,28,),\n    ([79, 99, 79, 85, 61, 58, 62, 61, 39, 87, 39, 74, 36, 70, 30, 43, 20, 52, 54, 50, 81, 98, 42],20,20,),\n    ([-98, -72, -46, -44, -42, -40, -16, -4, 62, 70, 74],8,10,),\n    ([1, 1, 0, 1, 0, 0, 0, 0, 1, 1, 0, 1, 0, 1, 1, 1, 1, 0, 0, 0, 1, 1, 0, 0, 0, 0, 1, 0, 0, 0, 0, 0, 0],26,23,),\n    ([58],0,0,),\n    ([4, -84, -42, 12, -50, 42, -36, -38, -36, 98, -2, 20, 6, -96, -78, 24, 34, 88, 0, 74, 0, -8, -86, -68, -42, 98, -26, 86, -70, -32, -82, 78, 46, 58, 84, 4, -60, -90, -52, -78],37,31,),\n    ([0, 0, 0, 0, 0, 0, 0, 0, 0, 0, 0, 0, 0, 1, 1, 1, 1, 1, 1, 1, 1, 1, 1, 1, 1, 1, 1, 1, 1],28,28,),\n    ([8],0,0,)\n        ]\n    n_success = 0\n    for i, parameters_set in enumerate(param):\n        if f_filled(*parameters_set) == f_gold(*parameters_set):\n            n_success+=1\n    print(\"#Results: %i, %i\" % (n_success, len(param)))", "ref": "def findFirstMissing ( array , start , end ) :\n    if ( start > end ) :\n        return end + 1\n    if ( start != array [ start ] ) :\n        return start ;\n    mid = int ( ( start + end ) / 2 )\n    if ( array [ mid ] == mid ) :\n        return findFirstMissing ( array , mid + 1 , end )\n    return findFirstMissing ( array , start , mid )\n"}
Disassembly of <code object findFirstMissing at 0x7f2b01639f60, file "<dis>", line 1>:
2 0 LOAD_FAST 1 ( start )
2 LOAD_FAST 2 ( end )
4 COMPARE_OP 4 ( > )
6 POP_JUMP_IF_FALSE 16

3 8 LOAD_FAST 2 ( end )
10 LOAD_CONST 1 ( 1 )
12 BINARY_ADD
14 RETURN_VALUE

4 >> 16 LOAD_FAST 1 ( start )
18 LOAD_FAST 0 ( array )
20 LOAD_FAST 1 ( start )
22 BINARY_SUBSCR
24 COMPARE_OP 3 ( != )
26 POP_JUMP_IF_FALSE 32

5 28 LOAD_FAST 1 ( start )
30 RETURN_VALUE

6 >> 32 LOAD_GLOBAL 0 ( int )
34 LOAD_FAST 1 ( start )
36 LOAD_FAST 2 ( end )
38 BINARY_ADD
40 LOAD_CONST 2 ( 2 )
42 BINARY_TRUE_DIVIDE
44 CALL_FUNCTION 1
46 STORE_FAST 3 ( mid )

7 48 LOAD_FAST 0 ( array )
50 LOAD_FAST 3 ( mid )
52 BINARY_SUBSCR
54 LOAD_FAST 3 ( mid )
56 COMPARE_OP 2 ( == )
58 POP_JUMP_IF_FALSE 70

8 60 LOAD_GLOBAL 1 ( findFirstMissing )
62 LOAD_FAST 0 ( array )
64 LOAD_FAST 3 ( mid )
66 LOAD_CONST 1 ( 1 )
68 BINARY_ADD
70 LOAD_FAST 2 ( end )
72 CALL_FUNCTION 3
74 RETURN_VALUE

9 >> 76 LOAD_GLOBAL 1 ( findFirstMissing )
78 LOAD_FAST 0 ( array )
80 LOAD_FAST 1 ( start )
82 LOAD_FAST 3 ( mid )
84 CALL_FUNCTION 3
86 RETURN_VALUE
