{"script": "# Copyright (c) 2019-present, Facebook, Inc.\n# All rights reserved.\n#\n# This source code is licensed under the license found in the\n# LICENSE file in the root directory of this source tree.\n#\ndef f_gold ( arr , n ) :\n    index = 0\n    while index < n :\n        if index == 0 :\n            index = index + 1\n        if arr [ index ] >= arr [ index - 1 ] :\n            index = index + 1\n        else :\n            arr [ index ] , arr [ index - 1 ] = arr [ index - 1 ] , arr [ index ]\n            index = index - 1\n    return arr\n\n\n#TOFILL\n\nif __name__ == '__main__':\n    param = [\n    ([5, 20, 27, 28, 31, 31, 31, 34, 49, 55, 61, 63, 68, 69, 73, 78, 78, 82, 85, 87, 98],17,),\n    ([34, -54, 0, 16, 66, -58, 88, -38, -94, -10],7,),\n    ([0, 0, 0, 0, 0, 0, 0, 0, 0, 0, 0, 0, 0, 0, 0, 0, 0, 0, 0, 0, 0, 1, 1, 1, 1, 1, 1, 1, 1, 1, 1, 1, 1, 1, 1, 1, 1, 1, 1, 1, 1, 1, 1, 1, 1],22,),\n    ([10, 28, 65, 98, 25, 25, 77, 46, 77, 54, 16, 43, 52, 75, 9, 15, 1, 72, 56, 75, 73, 45, 5, 78, 11, 3, 93, 73, 31, 69, 8, 89, 44, 58, 64, 36, 7, 4],26,),\n    ([-86, -50, -12, 26, 30, 68, 70, 80, 82],6,),\n    ([1, 1, 0, 0, 1, 1, 0, 1, 1, 0, 0, 1, 0, 1, 1, 0, 1, 0, 1, 1, 1, 0],17,),\n    ([14, 28, 29, 31, 41, 59, 60, 62, 66, 67, 70, 70, 74, 76, 92, 96],13,),\n    ([8, -22, 94, 28, 2, 14, 50, -54, 24, -26, -98, 58, -94, 4, -78, 98, 80, 72, -32, 58, -74],13,),\n    ([0, 0, 0, 0, 0, 0, 0, 0, 0, 0, 0, 0, 0, 0, 0, 0, 0, 0, 0, 0, 1, 1, 1, 1, 1, 1, 1, 1, 1, 1, 1, 1, 1, 1],24,),\n    ([3, 30, 84, 92, 29, 47, 36, 54, 93, 73, 53, 91, 81, 16, 51, 69, 82, 74, 80, 66, 77, 14, 85, 59, 86, 25, 85, 29, 19, 28, 13, 47, 61, 54, 13, 82, 52, 11, 10, 63, 52, 30, 35, 74],41,)\n        ]\n    n_success = 0\n    for i, parameters_set in enumerate(param):\n        if f_filled(*parameters_set) == f_gold(*parameters_set):\n            n_success+=1\n    print(\"#Results: %i, %i\" % (n_success, len(param)))", "ref": "def gnomeSort ( arr , n ) :\n    index = 0\n    while index < n :\n        if index == 0 :\n            index = index + 1\n        if arr [ index ] >= arr [ index - 1 ] :\n            index = index + 1\n        else :\n            arr [ index ] , arr [ index - 1 ] = arr [ index - 1 ] , arr [ index ]\n            index = index - 1\n    return arr\n"}
Disassembly of <code object gnomeSort at 0x7f2b0163dc90, file "<dis>", line 1>:
2 0 LOAD_CONST 1 ( 0 )
2 STORE_FAST 2 ( index )

3 4 SETUP_LOOP 88 ( to 94 )
>> 6 LOAD_FAST 2 ( index )
8 LOAD_FAST 2 ( index )
10 COMPARE_OP 0 ( < )
12 POP_JUMP_IF_FALSE 92

4 14 LOAD_FAST 2 ( index )
16 LOAD_CONST 1 ( 0 )
18 COMPARE_OP 2 ( == )
20 POP_JUMP_IF_FALSE 34

5 22 LOAD_FAST 2 ( index )
24 LOAD_CONST 2 ( 1 )
26 BINARY_ADD
28 STORE_FAST 2 ( index )
30 JUMP_ABSOLUTE 6
32 POP_BLOCK

6 >> 34 LOAD_FAST 0 ( arr )
36 LOAD_FAST 2 ( index )
38 BINARY_SUBSCR
40 LOAD_FAST 0 ( arr )
42 LOAD_FAST 2 ( index )
44 LOAD_CONST 2 ( 1 )
46 BINARY_SUBTRACT
48 BINARY_SUBSCR
50 COMPARE_OP 5 ( >= )
52 POP_JUMP_IF_FALSE 66

7 54 LOAD_FAST 2 ( index )
56 LOAD_CONST 2 ( 1 )
58 BINARY_ADD
60 STORE_FAST 2 ( index )
62 JUMP_ABSOLUTE 6
64 JUMP_FORWARD 30 ( to 92 )

9 >> 66 LOAD_FAST 0 ( arr )
68 LOAD_FAST 2 ( index )
70 LOAD_CONST 2 ( 1 )
72 BINARY_SUBTRACT
74 BINARY_SUBSCR
76 LOAD_FAST 0 ( arr )
78 LOAD_FAST 2 ( index )
80 BINARY_SUBSCR
82 ROT_TWO
84 LOAD_FAST 0 ( arr )
86 LOAD_FAST 2 ( index )
88 STORE_SUBSCR
90 LOAD_FAST 0 ( arr )
92 LOAD_FAST 2 ( index )
94 BINARY_SUBSCR
96 ROT_TWO
98 LOAD_FAST 0 ( arr )
100 LOAD_FAST 2 ( index )
102 STORE_SUBSCR

10 104 LOAD_FAST 2 ( index )
106 LOAD_CONST 2 ( 1 )
108 BINARY_SUBTRACT
110 STORE_FAST 2 ( index )
112 JUMP_ABSOLUTE 6
>> 114 POP_BLOCK

11 >> 116 LOAD_FAST 0 ( arr )
118 RETURN_VALUE
