{"script": "# Copyright (c) 2019-present, Facebook, Inc.\n# All rights reserved.\n#\n# This source code is licensed under the license found in the\n# LICENSE file in the root directory of this source tree.\n#\ndef f_gold ( arr , n ) :\n    arr.sort ( reverse = True )\n    dimension = [ 0 , 0 ]\n    i = 0\n    j = 0\n    while ( i < n - 1 and j < 2 ) :\n        if ( arr [ i ] == arr [ i + 1 ] ) :\n            dimension [ j ] = arr [ i ]\n            j += 1\n            i += 1\n        i += 1\n    return ( dimension [ 0 ] * dimension [ 1 ] )\n\n\n#TOFILL\n\nif __name__ == '__main__':\n    param = [\n    ([1, 5, 6, 8, 9, 11, 12, 14, 16, 17, 24, 25, 36, 40, 44, 47, 49, 51, 51, 52, 67, 68, 72, 74, 81, 82, 83, 84, 92, 95, 95, 96, 99],27,),\n    ([-54, -82, -92, -32],2,),\n    ([0, 0, 0, 0, 0, 0, 0, 0, 0, 0, 0, 0, 1, 1, 1, 1, 1, 1],15,),\n    ([16, 62, 17, 15, 26, 45, 2, 17, 65, 94, 96, 30, 68, 44, 96, 60, 99],8,),\n    ([-88, -82, -78, -52, -50, -42, -34, -28, 16, 46, 54, 56, 66, 66, 74, 82, 82, 94, 98],15,),\n    ([0, 1, 0, 0, 1, 0, 0, 1, 0, 1, 0, 0, 1, 0, 1, 0, 0, 1, 0, 1, 0, 1, 1, 1, 1, 0],18,),\n    ([1, 6, 8, 8, 8, 10, 13, 14, 14, 23, 24, 25, 27, 28, 29, 30, 33, 38, 43, 44, 49, 52, 56, 58, 62, 63, 64, 65, 65, 68, 75, 85, 85, 87, 93, 96, 97],20,),\n    ([-90, -56, 16, 32, 78, -20, 76, -90, -68, -70, 54, 50, 60, -64, 78, -6, -92, 6, 16, 70],19,),\n    ([0, 0, 0, 0, 0, 0, 0, 0, 0, 0, 0, 1, 1, 1, 1, 1, 1, 1, 1, 1, 1, 1, 1, 1, 1, 1, 1, 1, 1, 1, 1, 1, 1, 1],30,),\n    ([55, 51, 90, 10, 14, 5, 57, 22, 75, 29, 7, 18, 31, 43, 84, 35, 71, 94, 4, 51, 94, 30, 94, 53, 82],22,)\n        ]\n    n_success = 0\n    for i, parameters_set in enumerate(param):\n        if f_filled(*parameters_set) == f_gold(*parameters_set):\n            n_success+=1\n    print(\"#Results: %i, %i\" % (n_success, len(param)))", "ref": "def findArea ( arr , n ) :\n    arr.sort ( reverse = True )\n    dimension = [ 0 , 0 ]\n    i = 0\n    j = 0\n    while ( i < n - 1 and j < 2 ) :\n        if ( arr [ i ] == arr [ i + 1 ] ) :\n            dimension [ j ] = arr [ i ]\n            j += 1\n            i += 1\n        i += 1\n    return ( dimension [ 0 ] * dimension [ 1 ] )\n"}
Disassembly of <code object findArea at 0x7f2b01639f60, file "<dis>", line 1>:
2 0 LOAD_FAST 0 ( arr )
2 LOAD_ATTR 0 ( sort )
4 LOAD_CONST 1 ( True )
6 LOAD_CONST 2 ( ( 'reverse' , ) )
8 CALL_FUNCTION_KW 1
10 POP_TOP

3 12 LOAD_CONST 3 ( ( 0 , 0 ) )
14 BUILD_LIST 1
16 STORE_FAST 2 ( dimension )

4 18 LOAD_CONST 3 ( ( 0 ) )
20 STORE_FAST 3 ( i )

5 22 LOAD_CONST 3 ( 0 )
24 STORE_FAST 4 ( j )

6 26 SETUP_LOOP 68 ( to 96 )
>> 28 LOAD_FAST 3 ( i )
30 LOAD_FAST 1 ( n )
32 LOAD_CONST 4 ( 1 )
34 BINARY_SUBTRACT
36 COMPARE_OP 0 ( < )
38 POP_JUMP_IF_FALSE 94
40 LOAD_FAST 4 ( j )
42 LOAD_CONST 5 ( 2 )
44 COMPARE_OP 0 ( < )
46 POP_JUMP_IF_FALSE 94

7 48 LOAD_FAST 0 ( arr )
50 LOAD_FAST 3 ( i )
52 BINARY_SUBSCR
54 LOAD_FAST 0 ( arr )
56 LOAD_FAST 3 ( i )
58 LOAD_CONST 4 ( 1 )
60 BINARY_ADD
62 BINARY_SUBSCR
64 COMPARE_OP 2 ( == )
66 POP_JUMP_IF_FALSE 94

8 68 LOAD_FAST 0 ( arr )
70 LOAD_FAST 3 ( i )
72 BINARY_SUBSCR
74 LOAD_FAST 2 ( dimension )
76 LOAD_FAST 4 ( j )
78 STORE_SUBSCR

9 80 LOAD_FAST 4 ( j )
82 LOAD_CONST 4 ( 1 )
84 INPLACE_ADD
86 STORE_FAST 4 ( j )

10 88 LOAD_FAST 3 ( i )
90 LOAD_CONST 4 ( 1 )
92 INPLACE_ADD
96 STORE_FAST 3 ( i )

11 >> 98 LOAD_FAST 3 ( i )
100 LOAD_CONST 4 ( 1 )
102 INPLACE_ADD
104 STORE_FAST 3 ( i )
106 JUMP_ABSOLUTE 28
>> 108 POP_BLOCK

12 >> 110 LOAD_FAST 2 ( dimension )
112 LOAD_CONST 3 ( 0 )
114 BINARY_SUBSCR
116 LOAD_FAST 2 ( dimension )
118 LOAD_CONST 4 ( 1 )
120 BINARY_SUBSCR
122 BINARY_MULTIPLY
124 RETURN_VALUE
