{"script": "# Copyright (c) 2019-present, Facebook, Inc.\n# All rights reserved.\n#\n# This source code is licensed under the license found in the\n# LICENSE file in the root directory of this source tree.\n#\ndef f_gold ( n ) :\n    x = n\n    y = 1\n    e = 0.000001\n    while ( x - y > e ) :\n        x = ( x + y ) / 2\n        y = n / x\n    return x\n\n\n#TOFILL\n\nif __name__ == '__main__':\n    param = [\n    (1763.655093333857,),\n    (-3544.737136289062,),\n    (7893.209433000695,),\n    (-3008.0331952533734,),\n    (6155.190186637041,),\n    (-5799.751467314729,),\n    (8234.151546380555,),\n    (-1829.5367705266551,),\n    (5778.227173218819,),\n    (-7785.473710863676,)\n        ]\n    n_success = 0\n    for i, parameters_set in enumerate(param):\n        if abs(1 - (0.0000001 + abs(f_gold(*parameters_set))) / (abs(f_filled(*parameters_set)) + 0.0000001)) < 0.001:\n            n_success+=1\n    print(\"#Results: %i, %i\" % (n_success, len(param)))", "ref": "def squareRoot ( n ) :\n    x = n\n    y = 1\n    e = 0.000001\n    while ( x - y > e ) :\n        x = ( x + y ) / 2\n        y = n / x\n    return x\n"}
Disassembly of <code object squareRoot at 0x7f2b01639f60, file "<dis>", line 1>:
2 0 LOAD_FAST 0 ( n )
2 STORE_FAST 1 ( x )

3 4 LOAD_CONST 1 ( 1 )
6 STORE_FAST 2 ( y )

4 8 LOAD_CONST 2 ( 1e-06 )
10 STORE_FAST 3 ( e )

5 12 SETUP_LOOP 34 ( to 48 )
>> 14 LOAD_FAST 1 ( x )
16 LOAD_FAST 2 ( y )
18 BINARY_SUBTRACT
20 LOAD_FAST 3 ( e )
22 COMPARE_OP 4 ( > )
24 POP_JUMP_IF_FALSE 46

6 26 LOAD_FAST 1 ( x )
28 LOAD_FAST 2 ( y )
30 BINARY_ADD
32 LOAD_CONST 3 ( 2 )
34 BINARY_TRUE_DIVIDE
36 STORE_FAST 1 ( x )

7 38 LOAD_FAST 0 ( n )
40 LOAD_FAST 1 ( x )
42 BINARY_TRUE_DIVIDE
44 STORE_FAST 2 ( y )

8 >> 46 LOAD_FAST 1 ( x )
48 RETURN_VALUE
